{"result":{"status":{"code":0,"msg":"succ"},"timestamp":"Fri Jul 24 01:56:06 +0800 2026","top":[],"pdps":[],"cre":[],"total":101880,"end":1784824485,"start":1784828385,"lid":2509,"rtime":1784829366,"data":[{"icons":"","is_cre_manual":"0","hqChart":"{\"stockCharts\":\"no\",\"stockCode\":\"\",\"stockMarket\":\"\",\"mulStockChart\":\"\",\"isStaticStock\":\"\"}","intime":"1784828389","channelid":"31","ctime":"1784828385","mtime":"1784828385","authoruid":"0","level":"2","vid":"0","ipad_vid":"0","video_time_length":"0","categoryid":"1","mediaid":"0","templateid":"0","productid":"0","ext_0":"0","ext_1":"0","ext_2":"0","ext_3":"0","ext_4":"0","docid":"comos:niivpqx5171412","url":"https:\/\/finance.sina.com.cn\/stock\/usstock\/c\/2026-07-24\/doc-iniivpqx5171412.shtml","urls":"[\"https:\\\/\\\/finance.sina.com.cn\\\/stock\\\/usstock\\\/c\\\/2026-07-24\\\/doc-iniivpqx5171412.shtml\"]","wapurl":"https:\/\/finance.sina.cn\/usstock\/mggd\/2026-07-24\/detail-iniivpqx5171412.d.html","wapurls":"[\"https:\\\/\\\/finance.sina.cn\\\/usstock\\\/mggd\\\/2026-07-24\\\/detail-iniivpqx5171412.d.html\",\"http:\\\/\\\/finance.sina.cn\\\/usstock\\\/mggd\\\/2026-07-24\\\/detail-iniivpqx5171412.d.html\"]","wapsummary":"","title":"\u82f1\u7279\u5c14Q2\u8d22\u62a5\u524d\u77bb\uff1a\u5f3a\u52b2\u4e1a\u7ee9\u96be\u63a9\u4f30\u503c\u9690\u5fe7\uff0c\u5e02\u573a\u60c5\u7eea\u6210\u80a1\u4ef7\u5173\u952e\u53d8\u91cf","stitle":"","summary":"","intro":"\u82f1\u7279\u5c14\u516c\u53f8\u9884\u8ba1\u5c06\u516c\u5e03\u5f3a\u52b2\u7684\u7b2c\u4e8c\u5b63\u5ea6\u76c8\u5229\uff0c\u4f46\u5206\u6790\u6307\u51fa\uff0c\u5373\u4fbf\u4e1a\u7ee9\u4eae\u773c\uff0c\u4e5f\u53ef\u80fd\u4e0d\u8db3\u4ee5\u626d\u8f6c\u5176\u80a1\u4ef7\u57287\u6708\u4efd\u7684\u4e0b\u6ed1\u8d8b\u52bf\u3002\u672c\u6708\u82f1\u7279\u5c14\u80a1\u4ef7\u5df2\u4e0b\u8dcc\u7ea628%...","author":"","commentid":"cj:comos-niivpqx5171412:0","video_id":"","keywords":"","media_name":"\u73af\u7403\u5e02\u573a\u64ad\u62a5","columnid":"1850,2018,2032","subjectid":"","img":{"u":"http:\/\/n.sinaimg.cn\/finance\/c30320b4\/20210712\/wx_poster_finance1.png","w":100,"h":100,"t":""},"images":[],"lids":"295,747,1083,1084,1131,1134,2509,2516,2517,2518,2519,2544,2671,2672,2676,3318","oid":"877401167"},{"icons":"","is_cre_manual":"0","hqChart":"{\"stockCharts\":\"no\",\"stockCode\":\"\",\"stockMarket\":\"\",\"mulStockChart\":\"\",\"isStaticStock\":\"\"}","intime":"1784827526","channelid":"31","ctime":"1784827522","mtime":"1784827522","authoruid":"0","level":"2","vid":"0","ipad_vid":"0","video_time_length":"0","categoryid":"1","mediaid":"0","templateid":"0","productid":"0","ext_0":"0","ext_1":"0","ext_2":"0","ext_3":"0","ext_4":"0","docid":"comos:niivpqu9320301","url":"https:\/\/finance.sina.com.cn\/world\/2026-07-24\/doc-iniivpqu9320301.shtml","urls":"[\"https:\\\/\\\/finance.sina.com.cn\\\/world\\\/2026-07-24\\\/doc-iniivpqu9320301.shtml\"]","wapurl":"https:\/\/finance.sina.cn\/usstock\/mggd\/2026-07-24\/detail-iniivpqu9320301.d.html","wapurls":"[\"https:\\\/\\\/finance.sina.cn\\\/usstock\\\/mggd\\\/2026-07-24\\\/detail-iniivpqu9320301.d.html\",\"http:\\\/\\\/finance.sina.cn\\\/usstock\\\/mggd\\\/2026-07-24\\\/detail-iniivpqu9320301.d.html\"]","wapsummary":"","title":"\u6b27\u6d32\u503a\u5e02\uff1a\u6b27\u503a\u4e0b\u8dcc \u6cb9\u4ef7\u4e0a\u6da8\u63a8\u52a8\u52a0\u606f\u9884\u671f\u5347\u6e29","stitle":"","summary":"","intro":"\u968f\u7740\u6cb9\u4ef7\u81ea5\u6708\u4ee5\u6765\u9996\u6b21\u5347\u7834\u6bcf\u6876100\u7f8e\u5143\uff0c\u8d27\u5e01\u5e02\u573a\u5927\u5e45\u4e0a\u8c03\u5bf9\u592e\u884c\u52a0\u606f\u7684\u62bc\u6ce8\u3002\u4e92\u6362\u5408\u7ea6\u51e0\u4e4e\u5b8c\u5168\u8ba1\u5165\u6b27\u6d32\u592e\u884c\u57289\u6708\u548c12\u6708\u5206\u522b\u52a0\u606f25\u4e2a\u57fa\u70b9\u7684\u9884\u671f...","author":"","commentid":"cj:comos-niivpqu9320301:0","video_id":"0","keywords":"","media_name":"\u73af\u7403\u5e02\u573a\u64ad\u62a5","columnid":"1840,1850,1996,2018,2032","subjectid":"","img":{"u":"http:\/\/n.sinaimg.cn\/finance\/c30320b4\/20210712\/wx_poster_finance1.png","w":100,"h":100,"t":""},"images":[],"lids":"295,747,1059,1083,1084,1131,1134,2509,2516,2517,2518,2519,2544,2671,2672,2676,3076,3318","oid":"877398050","mlids":"","ext":"1"},{"icons":"","is_cre_manual":"0","hqChart":"{\"stockCharts\":\"no\",\"stockCode\":\"\",\"stockMarket\":\"\",\"mulStockChart\":\"\",\"isStaticStock\":\"\"}","intime":"1784826703","channelid":"31","ctime":"1784826695","mtime":"1784826701","authoruid":"0","level":"2","vid":"0","ipad_vid":"0","video_time_length":"0","categoryid":"1","mediaid":"0","templateid":"0","productid":"0","ext_0":"0","ext_1":"0","ext_2":"0","ext_3":"0","ext_4":"0","docid":"comos:niivpqx5156700","url":"https:\/\/finance.sina.com.cn\/stock\/usstock\/c\/2026-07-24\/doc-iniivpqx5156700.shtml","urls":"[\"https:\\\/\\\/finance.sina.com.cn\\\/stock\\\/usstock\\\/c\\\/2026-07-24\\\/doc-iniivpqx5156700.shtml\"]","wapurl":"https:\/\/finance.sina.cn\/usstock\/mggd\/2026-07-24\/detail-iniivpqx5156700.d.html","wapurls":"[\"https:\\\/\\\/finance.sina.cn\\\/usstock\\\/mggd\\\/2026-07-24\\\/detail-iniivpqx5156700.d.html\",\"http:\\\/\\\/finance.sina.cn\\\/usstock\\\/mggd\\\/2026-07-24\\\/detail-iniivpqx5156700.d.html\"]","wapsummary":"","title":"\u8c37\u6b4c\u4e91CEO\uff1a\u5ba2\u6237\u5b9e\u9645\u82b1\u9500\u8f83\u7b7e\u7ea6\u627f\u8bfa\u9ad8\u51fa\u4e94\u6210\uff0c\u4e91\u4e1a\u52a1\u4e1a\u7ee9\u5927\u5e45\u8d85\u51fa\u9884\u671f","stitle":"","summary":"","intro":"\u6838\u5fc3\u8981\u70b9 \u8c37\u6b4c\u4e91 CEO \u6258\u9a6c\u65af\u30fb\u5e93\u91cc\u5b89\u5468\u56db\u63a5\u53d7 \u91c7\u8bbf\u8868\u793a\uff0c\u5b58\u91cf\u5ba2\u6237\u5b9e\u9645\u4ed8\u8d39\u89c4\u6a21\u8f83\u4e8b\u524d\u7b7e\u7ea6\u627f\u8bfa\u989d\u5ea6\u9ad8\u51fa\u7ea6 50%\u3002 \u8be5\u56e0\u7d20\u52a9\u63a8\u8c37\u6b4c\u4e91\u8425\u6536\u540c\u6bd4\u66b4\u6da8 82%\uff0c\u5b9e\u73b0\u706b\u7206\u589e\u957f\u3002","author":"","commentid":"cj:comos-niivpqx5156700:0","video_id":"","keywords":"","media_name":"\u73af\u7403\u5e02\u573a\u64ad\u62a5","columnid":"1850,2018,2032","subjectid":"214673,214674","img":{"u":"http:\/\/n.sinaimg.cn\/finance\/c30320b4\/20210712\/wx_poster_finance1.png","w":100,"h":100,"t":""},"images":[],"lids":"295,747,1083,1084,1131,1134,2509,2516,2517,2518,2519,2544,2671,2672,2676,3318","oid":"877395171"},{"icons":"","is_cre_manual":"0","hqChart":"{\"stockCharts\":\"no\",\"stockCode\":\"\",\"stockMarket\":\"\",\"mulStockChart\":\"\",\"isStaticStock\":\"\"}","intime":"1784826586","channelid":"31","ctime":"1784826582","mtime":"1784826582","authoruid":"0","level":"2","vid":"0","ipad_vid":"0","video_time_length":"0","categoryid":"1","mediaid":"0","templateid":"0","productid":"0","ext_0":"0","ext_1":"0","ext_2":"0","ext_3":"0","ext_4":"0","docid":"comos:niivpqz1932429","url":"https:\/\/finance.sina.com.cn\/stock\/usstock\/c\/2026-07-24\/doc-iniivpqz1932429.shtml","urls":"[\"https:\\\/\\\/finance.sina.com.cn\\\/stock\\\/usstock\\\/c\\\/2026-07-24\\\/doc-iniivpqz1932429.shtml\"]","wapurl":"https:\/\/finance.sina.cn\/usstock\/mggd\/2026-07-24\/detail-iniivpqz1932429.d.html","wapurls":"[\"https:\\\/\\\/finance.sina.cn\\\/usstock\\\/mggd\\\/2026-07-24\\\/detail-iniivpqz1932429.d.html\",\"http:\\\/\\\/finance.sina.cn\\\/usstock\\\/mggd\\\/2026-07-24\\\/detail-iniivpqz1932429.d.html\"]","wapsummary":"","title":"\u514b\u83b1\u9ed8\u5766\u8a00\uff1a\u5f53\u524d\u5e02\u573a\u5f88\u96be\u627e\u5230\u4e70\u5165\u7406\u7531","stitle":"","summary":"","intro":"\u6838\u5fc3\u8981\u70b9 \u77e5\u540d\u4e3b\u6301\u4eba\u5409\u59c6\u30fb\u514b\u83b1\u9ed8\u8868\u793a\uff0c\u4e2d\u4e1c\u51b2\u7a81\u5347\u7ea7\u3001\u6cb9\u4ef7\u8d70\u9ad8\u3001\u5229\u7387\u4e0a\u884c\u3001\u4f01\u4e1a AI \u6295\u5165\u6fc0\u589e\uff0c\u5f53\u4e0b\u5e02\u573a\u6295\u8d44\u8005\u4e0d\u8be5\u592a\u8fc7\u4e50\u89c2\u3002 \u4ed6\u5728\u5468\u56db\u300a\u534e\u5c14\u8857\u76f4\u64ad\u5ba4\u300b\u8282\u76ee\u4e2d\u76f4\u8a00\uff1a\u201c\u6211\u5f88...","author":"","commentid":"cj:comos-niivpqz1932429:0","video_id":"","keywords":"","media_name":"\u73af\u7403\u5e02\u573a\u64ad\u62a5","columnid":"1850,2018,2032","subjectid":"","img":[],"images":[{"u":"http:\/\/n.sinaimg.cn\/finance\/transform\/59\/w550h309\/20260724\/f6ea-f436916e6fb06712303d1f67d31e27ae.png","w":"550","h":"309","t":""}],"lids":"295,747,1083,1084,1131,1134,2509,2516,2517,2518,2519,2544,2671,2672,2676,3318","oid":"877394778"},{"icons":"","is_cre_manual":"0","hqChart":"{\"stockCharts\":\"no\",\"stockCode\":\"\",\"stockMarket\":\"\",\"mulStockChart\":\"\",\"isStaticStock\":\"\"}","intime":"1784826458","channelid":"31","ctime":"1784826453","mtime":"1784826458","authoruid":"0","level":"2","vid":"0","ipad_vid":"0","video_time_length":"0","categoryid":"1","mediaid":"0","templateid":"0","productid":"0","ext_0":"0","ext_1":"0","ext_2":"0","ext_3":"0","ext_4":"0","docid":"comos:niivpqz1931179","url":"https:\/\/finance.sina.com.cn\/stock\/usstock\/c\/2026-07-24\/doc-iniivpqz1931179.shtml","urls":"[\"https:\\\/\\\/finance.sina.com.cn\\\/stock\\\/usstock\\\/c\\\/2026-07-24\\\/doc-iniivpqz1931179.shtml\"]","wapurl":"https:\/\/finance.sina.cn\/usstock\/mggd\/2026-07-24\/detail-iniivpqz1931179.d.html","wapurls":"[\"https:\\\/\\\/finance.sina.cn\\\/usstock\\\/mggd\\\/2026-07-24\\\/detail-iniivpqz1931179.d.html\",\"http:\\\/\\\/finance.sina.cn\\\/usstock\\\/mggd\\\/2026-07-24\\\/detail-iniivpqz1931179.d.html\"]","wapsummary":"","title":"\u76ee\u5149\u77ed\u6d45\u7684\u80a1\u5e02\u5df2\u65e0\u6cd5\u5bf9\u6218\u4e89\u98ce\u9669\u89c6\u800c\u4e0d\u89c1\uff1a\u6cb9\u4ef7\u7ad9\u4e0a100\u7f8e\u5143\uff0c\u5e02\u573a\u96be\u4ee5\u7ee7\u7eed\u5ffd\u7565","stitle":"","summary":"","intro":"\u6838\u5fc3\u8981\u70b9 \u5e03\u4f26\u7279\u539f\u6cb9\u518d\u5ea6\u7a81\u7834\u6bcf\u6876 100 \u7f8e\u5143\uff0c\u7f8e\u80a1\u5468\u56db\u96c6\u4f53\u4e0b\u8dcc\u3002 \u7f8e\u56fd\u8fde\u7eed 12 \u665a\u7a7a\u88ad\u4f0a\u6717\uff0c\u53e0\u52a0\u6c99\u7279\u8fd1\u6d77\u6cb9\u8f6e\u9047\u88ad\uff0c\u6cb9\u4ef7\u5e94\u58f0\u5927\u6da8\u3002","author":"","commentid":"cj:comos-niivpqz1931179:0","video_id":"","keywords":"","media_name":"\u73af\u7403\u5e02\u573a\u64ad\u62a5","columnid":"1850,2018,2032","subjectid":"","img":[],"images":[{"u":"http:\/\/n.sinaimg.cn\/finance\/transform\/59\/w550h309\/20260724\/3206-74676706f45d6f4ceaaca250de3b3b68.png","w":"550","h":"309","t":""},{"u":"http:\/\/n.sinaimg.cn\/finance\/transform\/50\/w550h300\/20260724\/1012-b30881bb18c2224d0e49609086f84b4f.png","w":"550","h":"300","t":""}],"lids":"295,747,1083,1084,1131,1134,2509,2516,2517,2518,2519,2544,2671,2672,2676,3318","oid":"877394398"},{"icons":"","is_cre_manual":"0","hqChart":"{\"stockCharts\":\"no\",\"stockCode\":\"\",\"stockMarket\":\"\",\"mulStockChart\":\"\",\"isStaticStock\":\"\"}","intime":"1784826314","channelid":"31","ctime":"1784826304","mtime":"1784826313","authoruid":"0","level":"2","vid":"0","ipad_vid":"0","video_time_length":"0","categoryid":"1","mediaid":"0","templateid":"0","productid":"0","ext_0":"0","ext_1":"0","ext_2":"0","ext_3":"0","ext_4":"0","docid":"comos:niivpqz1929711","url":"https:\/\/finance.sina.com.cn\/world\/2026-07-24\/doc-iniivpqz1929711.shtml","urls":"[\"https:\\\/\\\/finance.sina.com.cn\\\/world\\\/2026-07-24\\\/doc-iniivpqz1929711.shtml\"]","wapurl":"https:\/\/finance.sina.cn\/usstock\/mggd\/2026-07-24\/detail-iniivpqz1929711.d.html","wapurls":"[\"https:\\\/\\\/finance.sina.cn\\\/usstock\\\/mggd\\\/2026-07-24\\\/detail-iniivpqz1929711.d.html\",\"http:\\\/\\\/finance.sina.cn\\\/usstock\\\/mggd\\\/2026-07-24\\\/detail-iniivpqz1929711.d.html\"]","wapsummary":"","title":"Alphabet\u767e\u5e74\u503a\u9996\u6b21\u8dcc\u7834\u9762\u503c\u4e5d\u6210 \u8d85\u5927\u89c4\u6a21\u4e91\u670d\u52a1\u5546\u503a\u5238\u4fe1\u7528\u5229\u5dee\u8d70\u9614","stitle":"","summary":"","intro":" Alphabet Inc\uff0e\u4eca\u5e74\u65e9\u4e9b\u65f6\u5019\u5728\u5168\u7403\u5927\u4e3e\u53d1\u503a\u4e4b\u9645\uff0c\u4e8e\u82f1\u9551\u5e02\u573a\u53d1\u884c\u4e86\u4e00\u53ea100\u5e74\u671f\u503a\u5238\uff0c\u8fd9\u53ea\u503a\u5238\u4ef7\u683c\u9996\u6b21\u8dcc\u7834\u4e86\u6bcf\u82f1\u9551\u9762\u503c\u4e70\u4ef790\u4fbf\u58eb\u3002","author":"","commentid":"cj:comos-niivpqz1929711:0","video_id":"","keywords":"","media_name":"\u73af\u7403\u5e02\u573a\u64ad\u62a5","columnid":"1840,1850,1996,2018,2032","subjectid":"","img":[],"images":[{"u":"http:\/\/n.sinaimg.cn\/finance\/transform\/26\/w550h276\/20260724\/4c3a-a490ecf42cf2a77d3773342b7098c3ea.png","w":"550","h":"276","t":""}],"lids":"295,747,1059,1083,1084,1131,1134,2509,2516,2517,2518,2519,2544,2671,2672,2676,3076,3318","oid":"877393964","mlids":"","ext":"1"},{"icons":"","is_cre_manual":"0","hqChart":"{\"stockCharts\":\"no\",\"stockCode\":\"\",\"stockMarket\":\"\",\"mulStockChart\":\"\",\"isStaticStock\":\"\"}","intime":"1784826277","channelid":"31","ctime":"1784826265","mtime":"1784826276","authoruid":"0","level":"2","vid":"0","ipad_vid":"0","video_time_length":"0","categoryid":"1","mediaid":"0","templateid":"0","productid":"0","ext_0":"0","ext_1":"0","ext_2":"0","ext_3":"0","ext_4":"0","docid":"comos:niivpqu4478529","url":"https:\/\/finance.sina.com.cn\/stock\/usstock\/c\/2026-07-24\/doc-iniivpqu4478529.shtml","urls":"[\"https:\\\/\\\/finance.sina.com.cn\\\/stock\\\/usstock\\\/c\\\/2026-07-24\\\/doc-iniivpqu4478529.shtml\"]","wapurl":"https:\/\/finance.sina.cn\/usstock\/mggd\/2026-07-24\/detail-iniivpqu4478529.d.html","wapurls":"[\"https:\\\/\\\/finance.sina.cn\\\/usstock\\\/mggd\\\/2026-07-24\\\/detail-iniivpqu4478529.d.html\",\"http:\\\/\\\/finance.sina.cn\\\/usstock\\\/mggd\\\/2026-07-24\\\/detail-iniivpqu4478529.d.html\"]","wapsummary":"","title":"\u7279\u65af\u62c9\u80a1\u4ef7\u6216\u5c06\u521b\u4e0b2025\u5e746\u6708\u4ee5\u6765\u5355\u65e5\u6700\u5927\u8dcc\u5e45","stitle":"","summary":"","intro":" \u8fd9\u5bb6\u7535\u52a8\u6c7d\u8f66\u5382\u5546\u4e8c\u5b63\u5ea6\u4e1a\u7ee9\u4e0d\u53ca\u9884\u671f\uff0c\u540c\u65f6\u5ba3\u5e03\u5c06\u5927\u5e45\u52a0\u7801\u5f00\u652f\uff0c\u5f15\u53d1\u6295\u8d44\u8005\u6050\u614c\u3002\u7279\u65af\u62c9\u80a1\u4ef7\u5468\u56db\u5927\u8dcc 14%\uff0c\u5927\u6982\u7387\u521b\u4e0b 2025 \u5e74 6 \u6708\u4ee5\u6765\u6700\u60e8\u70c8\u7684\u5355\u65e5\u4e0b\u8dcc\u3002","author":"","commentid":"cj:comos-niivpqu4478529:0","video_id":"","keywords":"","media_name":"\u73af\u7403\u5e02\u573a\u64ad\u62a5","columnid":"1850,2018,2032","subjectid":"","img":{"u":"http:\/\/n.sinaimg.cn\/finance\/c30320b4\/20210712\/wx_poster_finance1.png","w":100,"h":100,"t":""},"images":[],"lids":"295,747,1083,1084,1131,1134,2509,2516,2517,2518,2519,2544,2671,2672,2676,3318","oid":"877393700"},{"icons":"","is_cre_manual":"0","hqChart":"{\"stockCharts\":\"no\",\"stockCode\":\"\",\"stockMarket\":\"\",\"mulStockChart\":\"\",\"isStaticStock\":\"\"}","intime":"1784826203","channelid":"31","ctime":"1784826198","mtime":"1784826198","authoruid":"0","level":"2","vid":"0","ipad_vid":"0","video_time_length":"0","categoryid":"1","mediaid":"0","templateid":"0","productid":"0","ext_0":"0","ext_1":"0","ext_2":"0","ext_3":"0","ext_4":"0","docid":"comos:niivpqx5152070","url":"https:\/\/finance.sina.com.cn\/world\/2026-07-24\/doc-iniivpqx5152070.shtml","urls":"[\"https:\\\/\\\/finance.sina.com.cn\\\/world\\\/2026-07-24\\\/doc-iniivpqx5152070.shtml\"]","wapurl":"https:\/\/finance.sina.cn\/usstock\/mggd\/2026-07-24\/detail-iniivpqx5152070.d.html","wapurls":"[\"https:\\\/\\\/finance.sina.cn\\\/usstock\\\/mggd\\\/2026-07-24\\\/detail-iniivpqx5152070.d.html\",\"http:\\\/\\\/finance.sina.cn\\\/usstock\\\/mggd\\\/2026-07-24\\\/detail-iniivpqx5152070.d.html\"]","wapsummary":"","title":"\u6b27\u6d32\u80a1\u5e02\u6536\u8dcc \u6cb9\u4ef7\u98d9\u5347\u4e0e\u4f01\u4e1a\u4e1a\u7ee9\u62d6\u7d2f\u5e02\u573a","stitle":"","summary":"","intro":"\u6b27\u6d32\u80a1\u5e02\u6536\u8dcc\uff0c\u6700\u65b0\u4f01\u4e1a\u4e1a\u7ee9\u62d6\u7d2f\u79d1\u6280\u80a1\u548c\u5fc5\u9700\u6d88\u8d39\u54c1\u80a1\u8868\u73b0\uff0c\u800c\u7f8e\u4f0a\u7d27\u5f20\u5c40\u52bf\u5347\u7ea7\u63a8\u52a8\u6cb9\u4ef7\u4e0a\u6da8\u4e5f\u4ee4\u57fa\u51c6\u80a1\u6307\u627f\u538b\u3002 \u65af\u6258\u514b\u6b27\u6d32600\u6307\u6570\u6536\u8dcc1.2%\u3002","author":"","commentid":"cj:comos-niivpqx5152070:0","video_id":"","keywords":"","media_name":"\u73af\u7403\u5e02\u573a\u64ad\u62a5","columnid":"1840,1850,2018,2032","subjectid":"","img":[],"images":[{"u":"http:\/\/n.sinaimg.cn\/finance\/transform\/43\/w550h293\/20260724\/02bf-c1f65af0bddf78e9ac5de264864beb01.png","w":"550","h":"293","t":""}],"lids":"295,747,1059,1083,1084,1131,1134,2509,2516,2517,2518,2519,2544,2671,2672,2676,3076,3318","oid":"877393459"},{"icons":"","is_cre_manual":"0","hqChart":"{\"stockCharts\":\"no\",\"stockCode\":\"\",\"stockMarket\":\"\",\"mulStockChart\":\"\",\"isStaticStock\":\"\"}","intime":"1784826048","channelid":"31","ctime":"1784826044","mtime":"1784826044","authoruid":"0","level":"2","vid":"0","ipad_vid":"0","video_time_length":"0","categoryid":"1","mediaid":"0","templateid":"0","productid":"0","ext_0":"0","ext_1":"0","ext_2":"0","ext_3":"0","ext_4":"0","docid":"comos:niiusky8308016","url":"https:\/\/finance.sina.com.cn\/consume\/xiaofei\/2026-07-24\/doc-iniiusky8308016.shtml","urls":"[\"https:\\\/\\\/finance.sina.com.cn\\\/consume\\\/xiaofei\\\/2026-07-24\\\/doc-iniiusky8308016.shtml\"]","wapurl":"https:\/\/finance.sina.cn\/consume\/shxf\/2026-07-24\/detail-iniiusky8308016.d.html","wapurls":"[\"https:\\\/\\\/finance.sina.cn\\\/consume\\\/shxf\\\/2026-07-24\\\/detail-iniiusky8308016.d.html\",\"http:\\\/\\\/finance.sina.cn\\\/consume\\\/shxf\\\/2026-07-24\\\/detail-iniiusky8308016.d.html\"]","wapsummary":"","title":"\u76f4\u64ad\u5e26\u8d27\u8e29\u5751\u600e\u4e48\u529e\uff1f\u6559\u4f60\u51e0\u62db\u6709\u6548\u7ef4\u6743","stitle":"","summary":"","intro":"\u76f4\u64ad\u5e26\u8d27\u8fd9\u51e0\u5e74\u706b\u5f97\u4e00\u584c\u7cca\u6d82\uff0c\u4f46\u968f\u4e4b\u800c\u6765\u7684\u6d88\u8d39\u7ea0\u7eb7\u4e5f\u8d8a\u6765\u8d8a\u591a\u3002\u6700\u8fd1\u5c31\u6709\u65b0\u95fb\u66dd\u5149\uff0c\u6709\u4e3b\u64ad\u6253\u7740\u6551\u52a9\u6d41\u6d6a\u52a8\u7269\u7684\u65d7\u53f7\u5356\u72d7\u7cae\uff0c\u58f0\u79f0\u4f1a\u76f4\u63a5\u9001\u5230\u6551\u52a9\u7ad9...","author":"","commentid":"cj:comos-niiusky8308016:0","video_id":"","keywords":"","media_name":"\u65b0\u6d6a\u8d22\u7ecf","columnid":"1915,1920","subjectid":"","img":[],"images":[],"lids":"295,1703,1705,2509,2519,2544,3318","oid":"877393027"},{"icons":"","is_cre_manual":"0","hqChart":"{\"stockCharts\":\"no\",\"stockCode\":\"\",\"stockMarket\":\"\",\"mulStockChart\":\"\",\"isStaticStock\":\"\"}","intime":"1784824770","channelid":"31","ctime":"1784824767","mtime":"1784824767","authoruid":"0","level":"2","vid":"0","ipad_vid":"0","video_time_length":"0","categoryid":"1","mediaid":"0","templateid":"0","productid":"0","ext_0":"0","ext_1":"0","ext_2":"0","ext_3":"0","ext_4":"0","docid":"comos:niivpqx5142584","url":"https:\/\/finance.sina.com.cn\/stock\/usstock\/c\/2026-07-24\/doc-iniivpqx5142584.shtml","urls":"[\"https:\\\/\\\/finance.sina.com.cn\\\/stock\\\/usstock\\\/c\\\/2026-07-24\\\/doc-iniivpqx5142584.shtml\"]","wapurl":"https:\/\/finance.sina.cn\/usstock\/mggd\/2026-07-24\/detail-iniivpqx5142584.d.html","wapurls":"[\"https:\\\/\\\/finance.sina.cn\\\/usstock\\\/mggd\\\/2026-07-24\\\/detail-iniivpqx5142584.d.html\",\"http:\\\/\\\/finance.sina.cn\\\/usstock\\\/mggd\\\/2026-07-24\\\/detail-iniivpqx5142584.d.html\"]","wapsummary":"","title":"\u52a0\u62ff\u5927\u7687\u5bb6\u94f6\u884c\uff1a\u4e2d\u4e1c\u5c40\u52bf\u5347\u7ea7\uff0c\u6cb9\u4ef7\u6216\u98d9\u5347\u81f3128\u7f8e\u5143\u4ee5\u4e0a","stitle":"","summary":"","intro":" \u52a0\u62ff\u5927\u7687\u5bb6\u94f6\u884c\u8d44\u672c\u5e02\u573a\uff08RBC Capital Markets\uff09\u8868\u793a\uff0c\u7ea2\u6d77\u6cb9\u8f6e\u63a5\u8fde\u9047\u88ad\u3001\u4f0a\u6717\u6253\u51fb\u6ce2\u65af\u6e7e\u5173\u952e\u57fa\u7840\u8bbe\u65bd\uff0c\u7f8e\u56fd\u4e0e\u4f0a\u6717\u7684\u5bf9\u6297\u5df2\u7ecf\u6b65\u5165\u98ce\u9669\u66f4\u9ad8\u7684\u9636\u6bb5\u3002","author":"","commentid":"cj:comos-niivpqx5142584:0","video_id":"","keywords":"","media_name":"\u73af\u7403\u5e02\u573a\u64ad\u62a5","columnid":"1850,2018,2032","subjectid":"","img":{"u":"http:\/\/n.sinaimg.cn\/finance\/c30320b4\/20210712\/wx_poster_finance1.png","w":100,"h":100,"t":""},"images":[],"lids":"295,747,1083,1084,1131,1134,2509,2516,2517,2518,2519,2544,2671,2672,2676,3318","oid":"877389135"},{"icons":"","is_cre_manual":"0","hqChart":"{\"stockCharts\":\"no\",\"stockCode\":\"\",\"stockMarket\":\"\",\"mulStockChart\":\"\",\"isStaticStock\":\"\"}","intime":"1784824681","channelid":"31","ctime":"1784824675","mtime":"1784824680","authoruid":"0","level":"2","vid":"0","ipad_vid":"0","video_time_length":"0","categoryid":"1","mediaid":"0","templateid":"0","productid":"0","ext_0":"0","ext_1":"0","ext_2":"0","ext_3":"0","ext_4":"0","docid":"comos:niivpqz1918605","url":"https:\/\/finance.sina.com.cn\/stock\/usstock\/c\/2026-07-24\/doc-iniivpqz1918605.shtml","urls":"[\"https:\\\/\\\/finance.sina.com.cn\\\/stock\\\/usstock\\\/c\\\/2026-07-24\\\/doc-iniivpqz1918605.shtml\"]","wapurl":"https:\/\/finance.sina.cn\/usstock\/mggd\/2026-07-24\/detail-iniivpqz1918605.d.html","wapurls":"[\"https:\\\/\\\/finance.sina.cn\\\/usstock\\\/mggd\\\/2026-07-24\\\/detail-iniivpqz1918605.d.html\",\"http:\\\/\\\/finance.sina.cn\\\/usstock\\\/mggd\\\/2026-07-24\\\/detail-iniivpqz1918605.d.html\"]","wapsummary":"","title":"\u9a6c\u65af\u514b\u91ca\u653e\u7279\u65af\u62c9\u4e0e\u592a\u7a7a\u63a2\u7d22\u6280\u672f\u516c\u53f8\u5408\u4f5c\u6df1\u5316\u4fe1\u53f7\uff0c\u4f46\u62d2\u7edd\u8ba8\u8bba\u4e24\u5bb6\u4f01\u4e1a\u5408\u5e76\u4e8b\u5b9c","stitle":"","summary":"","intro":"\u6839\u636e\u8def\u5b5a\u7279\u6574\u7406\u7684\u6587\u5b57\u5b9e\u5f55\uff0c\u57c3\u9686\u30fb\u9a6c\u65af\u514b\u5728\u5468\u4e09\u665a\u95f4\u7279\u65af\u62c9\u8d22\u62a5\u7535\u8bdd\u4f1a\u4e0a\u8868\u793a\uff0c\u7279\u65af\u62c9\u4e0e\u592a\u7a7a\u63a2\u7d22\u6280\u672f\u516c\u53f8\uff08SpaceX\uff09\u6b63\u5728\u591a\u4e2a\u9879\u76ee\u7ef4\u5ea6\u6df1\u5316\u5408\u4f5c...","author":"","commentid":"cj:comos-niivpqz1918605:0","video_id":"","keywords":"","media_name":"\u73af\u7403\u5e02\u573a\u64ad\u62a5","columnid":"1850,2018,2032","subjectid":"","img":[],"images":[{"u":"http:\/\/n.sinaimg.cn\/finance\/transform\/59\/w550h309\/20260724\/21a2-ef2ef206da9ceada71425af92cd655ea.png","w":"550","h":"309","t":"2026 \u5e74 7 \u6708 20 \u65e5\uff0c\u7f8e\u56fd\u5f97\u514b\u8428\u65af\u5dde\u661f\u57fa\u5730\u592a\u7a7a\u53d1\u5c04\u5236\u9020\u5382\u533a\u5916\u7684\u5145\u7535\u7ad9\u505c\u653e\u7740\u4e00\u961f\u7279\u65af\u62c9\u8d5b\u535a\u76ae\u5361\u3002"}],"lids":"295,747,1083,1084,1131,1134,2509,2516,2517,2518,2519,2544,2671,2672,2676,3318","oid":"877388699"},{"icons":"","is_cre_manual":"0","hqChart":"{\"stockCharts\":\"no\",\"stockCode\":\"\",\"stockMarket\":\"\",\"mulStockChart\":\"\",\"isStaticStock\":\"\"}","intime":"1784825915","channelid":"31","ctime":"1784824632","mtime":"1784825906","authoruid":"0","level":"2","vid":"0","ipad_vid":"0","video_time_length":"0","categoryid":"1","mediaid":"0","templateid":"0","productid":"0","ext_0":"0","ext_1":"0","ext_2":"0","ext_3":"0","ext_4":"0","docid":"comos:niivpqz1918287","url":"https:\/\/finance.sina.com.cn\/world\/2026-07-24\/doc-iniivpqz1918287.shtml","urls":"[\"https:\\\/\\\/finance.sina.com.cn\\\/world\\\/2026-07-24\\\/doc-iniivpqz1918287.shtml\"]","wapurl":"https:\/\/finance.sina.cn\/usstock\/mggd\/2026-07-24\/detail-iniivpqz1918287.d.html","wapurls":"[\"https:\\\/\\\/finance.sina.cn\\\/usstock\\\/mggd\\\/2026-07-24\\\/detail-iniivpqz1918287.d.html\",\"http:\\\/\\\/finance.sina.cn\\\/usstock\\\/mggd\\\/2026-07-24\\\/detail-iniivpqz1918287.d.html\"]","wapsummary":"","title":"\u4e4c\u514b\u5170\u52a0\u7801\u653b\u51fb\u80fd\u6e90\u8bbe\u65bd\u540e \u4fc4\u7f57\u65af\u636e\u62a5\u8003\u8651\u5ef6\u957f\u67f4\u6cb9\u51fa\u53e3\u7981\u4ee4","stitle":"","summary":"","intro":"\u636e\u56fd\u9645\u6587\u4f20\u7535\u8baf\u793e\u62a5\u9053\uff0c\u968f\u7740\u4e4c\u514b\u5170\u52a0\u5927\u5bf9\u4fc4\u7f57\u65af\u77f3\u6cb9\u884c\u4e1a\u7684\u653b\u51fb\u529b\u5ea6\uff0c\u4fc4\u7f57\u65af\u6b63\u8003\u8651\u5c06\u67f4\u6cb9\u51fa\u53e3\u7981\u4ee4\u518d\u5ef6\u957f\u4e00\u4e2a\u6708\u3002 \u4fc4\u7f57\u65af\u662f\u5168\u7403\u4e3b\u8981\u67f4\u6cb9\u4f9b\u5e94\u56fd...","author":"","commentid":"cj:comos-niivpqz1918287:0","video_id":"","keywords":"","media_name":"\u73af\u7403\u5e02\u573a\u64ad\u62a5","columnid":"1840,1850,2018,2032","subjectid":"","img":{"u":"http:\/\/n.sinaimg.cn\/finance\/c30320b4\/20210712\/wx_poster_finance1.png","w":100,"h":100,"t":""},"images":[],"lids":"295,747,1059,1083,1084,1131,1134,2509,2516,2517,2518,2519,2544,2671,2672,2676,3076,3318","oid":"877388435"},{"icons":"","is_cre_manual":"0","hqChart":"{\"stockCharts\":\"no\",\"stockCode\":\"\",\"stockMarket\":\"\",\"mulStockChart\":\"\",\"isStaticStock\":\"\"}","intime":"1784825930","channelid":"31","ctime":"1784824594","mtime":"1784825926","authoruid":"0","level":"2","vid":"0","ipad_vid":"0","video_time_length":"0","categoryid":"1","mediaid":"0","templateid":"0","productid":"0","ext_0":"0","ext_1":"0","ext_2":"0","ext_3":"0","ext_4":"0","docid":"comos:niivpqz1918113","url":"https:\/\/finance.sina.com.cn\/world\/2026-07-24\/doc-iniivpqz1918113.shtml","urls":"[\"https:\\\/\\\/finance.sina.com.cn\\\/world\\\/2026-07-24\\\/doc-iniivpqz1918113.shtml\"]","wapurl":"https:\/\/finance.sina.cn\/usstock\/mggd\/2026-07-24\/detail-iniivpqz1918113.d.html","wapurls":"[\"https:\\\/\\\/finance.sina.cn\\\/usstock\\\/mggd\\\/2026-07-24\\\/detail-iniivpqz1918113.d.html\",\"http:\\\/\\\/finance.sina.cn\\\/usstock\\\/mggd\\\/2026-07-24\\\/detail-iniivpqz1918113.d.html\"]","wapsummary":"","title":"\u57fa\u5dee\u4ea4\u6613\u201c\u5df2\u6b7b\u201d\uff1f\u5bf9\u51b2\u57fa\u91d1\u949f\u7231\u7684\u7f8e\u503a\u62bc\u6ce8\u7b56\u7565\u663e\u9732\u75b2\u6001","stitle":"","summary":"","intro":"\u5bf9\u51b2\u57fa\u91d1\u5728\u7f8e\u56fd\u503a\u5238\u5e02\u573a\u6700\u70ed\u95e8\u7684\u4ea4\u6613\u7b56\u7565\u663e\u9732\u51fa\u63a5\u8fd1\u5bb9\u91cf\u4e0a\u9650\u7684\u8ff9\u8c61\u3002 \u8fd9\u79cd\u88ab\u79f0\u4e3a\u57fa\u5dee\u4ea4\u6613\u7684\u7b56\u7565\u4e3b\u8981\u62bc\u6ce8\u7f8e\u56fd\u56fd\u503a\u671f\u8d27\u4e0e\u5bf9\u5e94\u73b0\u5238\u4e4b\u95f4\u7684\u5fae\u5c0f\u4ef7\u5dee...","author":"","commentid":"cj:comos-niivpqz1918113:0","video_id":"","keywords":"","media_name":"\u73af\u7403\u5e02\u573a\u64ad\u62a5","columnid":"1840,1850,1966,1975,1996,2018,2032","subjectid":"","img":[],"images":[{"u":"http:\/\/n.sinaimg.cn\/finance\/transform\/164\/w550h414\/20260724\/55c3-423d11c008c58f2507dcd5dda15b2b93.png","w":"550","h":"414","t":""},{"u":"https:\/\/n.sinaimg.cn\/finance\/transform\/59\/w550h309\/20260724\/2982-48a7fb08bb8bb1c5e2c2674abd477995.jpg","w":"550","h":"309","t":""}],"lids":"295,747,1059,1083,1084,1131,1134,2487,2509,2516,2517,2518,2519,2544,2671,2672,2676,3076,3318","oid":"877388257"},{"icons":"","is_cre_manual":"0","hqChart":"{\"stockCharts\":\"no\",\"stockCode\":\"\",\"stockMarket\":\"\",\"mulStockChart\":\"\",\"isStaticStock\":\"\"}","intime":"1784824571","channelid":"31","ctime":"1784824568","mtime":"1784824570","authoruid":"0","level":"2","vid":"0","ipad_vid":"0","video_time_length":"0","categoryid":"1","mediaid":"0","templateid":"0","productid":"0","ext_0":"0","ext_1":"0","ext_2":"0","ext_3":"0","ext_4":"0","docid":"comos:niivpqu4462116","url":"https:\/\/finance.sina.com.cn\/stock\/usstock\/c\/2026-07-24\/doc-iniivpqu4462116.shtml","urls":"[\"https:\\\/\\\/finance.sina.com.cn\\\/stock\\\/usstock\\\/c\\\/2026-07-24\\\/doc-iniivpqu4462116.shtml\"]","wapurl":"https:\/\/finance.sina.cn\/usstock\/mggd\/2026-07-24\/detail-iniivpqu4462116.d.html","wapurls":"[\"https:\\\/\\\/finance.sina.cn\\\/usstock\\\/mggd\\\/2026-07-24\\\/detail-iniivpqu4462116.d.html\",\"http:\\\/\\\/finance.sina.cn\\\/usstock\\\/mggd\\\/2026-07-24\\\/detail-iniivpqu4462116.d.html\"]","wapsummary":"","title":"\u6563\u6237\u6295\u8d44\u8005\u770b\u6da8\u60c5\u7eea\u8dcc\u81f3\u53bb\u5e74 9 \u6708\u4ee5\u6765\u6700\u4f4e\u6c34\u5e73","stitle":"","summary":"","intro":"\u7f8e\u56fd\u4e2a\u4eba\u6295\u8d44\u8005\u534f\u4f1a\uff08AAII\uff09\u6700\u65b0\u4e00\u5468\u8c03\u67e5\u663e\u793a\uff0c\u53d7\u8bbf\u6563\u6237\u6295\u8d44\u8005\u4e2d\u770b\u6da8\u7f8e\u80a1\u6bd4\u4f8b\u9aa4\u964d\u81f3 29.6%\uff0c\u8f83\u524d\u4e00\u5468\u7684 44.9% \u5927\u5e45\u56de\u843d\uff0c\u521b\u4e0b\u53bb\u5e74 9 \u6708\u4ee5\u6765\u65b0\u4f4e\u3002","author":"","commentid":"cj:comos-niivpqu4462116:0","video_id":"0","keywords":"","media_name":"\u73af\u7403\u5e02\u573a\u64ad\u62a5","columnid":"1850,2018,2032","subjectid":"","img":{"u":"http:\/\/n.sinaimg.cn\/finance\/c30320b4\/20210712\/wx_poster_finance1.png","w":100,"h":100,"t":""},"images":[],"lids":"295,747,1083,1084,1131,1134,2509,2516,2517,2518,2519,2544,2671,2672,2676,3318","oid":"877388219","mlids":"","ext":"1"},{"oid":"877387762","docid":"comos:niivpqu9288359","url":"https:\/\/finance.sina.com.cn\/stock\/usstock\/c\/2026-07-24\/doc-iniivpqu9288359.shtml","wapurl":"https:\/\/finance.sina.cn\/usstock\/mggd\/2026-07-24\/detail-iniivpqu9288359.d.html","title":"\u5e03\u4f26\u7279\u539f\u6cb9\u7a81\u7834100\u7f8e\u5143\u5173\u53e3\uff0c\u7279\u6717\u666e\u5728\u4e2d\u4e1c\u53ea\u5269\u4e24\u6761\u8def\u53ef\u9009","stitle":"","summary":"","wapsummary":"","intro":" \u7279\u6717\u666e\u653f\u5e9c\u56e0\u4e5f\u95e8\u53d7\u4f0a\u6717\u6276\u6301\u7684\u80e1\u585e\u6b66\u88c5\u88ad\u51fb\u7ea2\u6d77\u4e24\u8258\u6c99\u7279\u8239\u53ea\uff0c\u626c\u8a00\u6253\u51fb\u4f0a\u6717\u57fa\u7840\u8bbe\u65bd\u3002\u53d7\u6b64\u5f71\u54cd\uff0c7 \u6708\u4ea4\u5272\u7684\u5e03\u4f26\u7279\u539f\u6cb9\u671f\u8d27\u81ea 5 \u6708 26 \u65e5\u4ee5\u6765\u9996\u6b21\u7ad9\u4e0a\u6bcf\u6876 100 \u7f8e\u5143\u3002","ctime":"1784824485","mtime":"1784824488","intime":"1784824489","author":"","authoruid":"0","level":"2","img":{"u":"http:\/\/n.sinaimg.cn\/finance\/c30320b4\/20210712\/wx_poster_finance1.png","w":100,"h":100,"t":""},"images":[],"commentid":"cj:comos-niivpqu9288359:0","vid":"0","ipad_vid":"0","keywords":"","categoryid":"1","channelid":"31","mediaid":"0","columnid":"1850,1978,2018,2032","subjectid":"","templateid":"0","productid":"0","lids":"295,747,1083,1084,1107,1131,1134,2509,2516,2517,2518,2519,2544,2671,2672,2676,3318","mlids":"","ext_0":"0","ext_1":"0","ext_2":"0","ext_3":"0","ext_4":"0","ext":"1","media_name":"\u73af\u7403\u5e02\u573a\u64ad\u62a5","video_id":"","video_time_length":"0","urls":"[\"https:\\\/\\\/finance.sina.com.cn\\\/stock\\\/usstock\\\/c\\\/2026-07-24\\\/doc-iniivpqu9288359.shtml\"]","wapurls":"[\"https:\\\/\\\/finance.sina.cn\\\/usstock\\\/mggd\\\/2026-07-24\\\/detail-iniivpqu9288359.d.html\",\"http:\\\/\\\/finance.sina.cn\\\/usstock\\\/mggd\\\/2026-07-24\\\/detail-iniivpqu9288359.d.html\"]","hqChart":"{\"stockCharts\":\"no\",\"stockCode\":\"\",\"stockMarket\":\"\",\"mulStockChart\":\"\",\"isStaticStock\":\"\"}","icons":"","is_cre_manual":"0","comment_reply":0,"comment_show":2,"comment_total":2}]}}