{"result":{"status":{"code":0,"msg":"succ"},"timestamp":"Tue Jun 30 06:59:41 +0800 2026","top":[],"pdps":[],"cre":[],"total":100014,"end":1782765869,"start":1782773798,"lid":2509,"rtime":1782773981,"data":[{"icons":"","is_cre_manual":"0","hqChart":"{\"stockCharts\":\"no\",\"stockCode\":\"\",\"stockMarket\":\"\",\"mulStockChart\":\"\",\"isStaticStock\":\"\"}","intime":"1782773835","channelid":"31","ctime":"1782773798","mtime":"1782773834","authoruid":"0","level":"2","vid":"0","ipad_vid":"0","video_time_length":"0","categoryid":"1","mediaid":"0","templateid":"0","productid":"0","ext_0":"0","ext_1":"0","ext_2":"0","ext_3":"0","ext_4":"0","docid":"comos:nifcrne1785026","url":"https:\/\/finance.sina.com.cn\/stock\/usstock\/c\/2026-06-30\/doc-inifcrne1785026.shtml","urls":"[\"https:\\\/\\\/finance.sina.com.cn\\\/stock\\\/usstock\\\/c\\\/2026-06-30\\\/doc-inifcrne1785026.shtml\"]","wapurl":"https:\/\/finance.sina.cn\/usstock\/mggd\/2026-06-30\/detail-inifcrne1785026.d.html","wapurls":"[\"https:\\\/\\\/finance.sina.cn\\\/usstock\\\/mggd\\\/2026-06-30\\\/detail-inifcrne1785026.d.html\",\"http:\\\/\\\/finance.sina.cn\\\/usstock\\\/mggd\\\/2026-06-30\\\/detail-inifcrne1785026.d.html\"]","wapsummary":"","title":"6\u670830\u65e5\u9694\u591c\u8981\u95fb\uff1a\u7f8e\u80a1\u6536\u9ad8\u79d1\u6280\u80a1\u9886\u6da8 \u6cb9\u4ef7\u4e0a\u6da8 \u4f26\u94dc\u4e0b\u6ed1 \u9ec4\u91d1\u8d70\u4f4e \u65e5\u5143\u5151\u7f8e\u5143\u8dcc\u81f3\u8fd140\u5e74\u4f4e\u70b9","stitle":"","summary":"","intro":"\u5e02\u573a 6\u670830\u65e5\u6536\u76d8\uff1a\u7f8e\u80a1\u6536\u9ad8\u79d1\u6280\u80a1\u9886\u6da8\uff0c\u7eb3\u6307\u4e0a\u6da82.07% 6\u670830\u65e5\u7f8e\u80a1\u6210\u4ea4\u989d\u524d20\uff1a\u745e\u94f6\u4e0a\u8c03\u53f0\u79ef\u7535\u76ee\u6807\u4ef7 6\u670830\u65e5\u70ed\u95e8\u4e2d\u6982\u80a1\u591a\u6570\u4e0a\u6da8 \u53f0\u79ef\u7535\u6da85.24%\uff0c\u767e\u5ea6\u6da87...","author":"","commentid":"cj:comos-nifcrne1785026:0","video_id":"","keywords":"","media_name":"\u73af\u7403\u5e02\u573a\u64ad\u62a5","columnid":"1840,1850,1978,2018,2032,2048","subjectid":"","img":[],"images":[{"u":"http:\/\/n.sinaimg.cn\/finance\/transform\/20151229\/HltM-fxmykrf2567298.png","w":400,"h":300,"t":""}],"lids":"295,747,1059,1083,1084,1107,1131,1134,2509,2516,2517,2518,2519,2544,2671,2672,2676,3076,3318","oid":"869174756"},{"icons":"","is_cre_manual":"0","hqChart":"{\"stockCharts\":\"no\",\"stockCode\":\"\",\"stockMarket\":\"\",\"mulStockChart\":\"\",\"isStaticStock\":\"\"}","intime":"1782773068","channelid":"31","ctime":"1782773049","mtime":"1782773063","authoruid":"0","level":"2","vid":"0","ipad_vid":"0","video_time_length":"0","categoryid":"1","mediaid":"0","templateid":"0","productid":"0","ext_0":"0","ext_1":"0","ext_2":"0","ext_3":"0","ext_4":"0","docid":"comos:nifcrna5003876","url":"https:\/\/finance.sina.com.cn\/stock\/usstock\/c\/2026-06-30\/doc-inifcrna5003876.shtml","urls":"[\"https:\\\/\\\/finance.sina.com.cn\\\/stock\\\/usstock\\\/c\\\/2026-06-30\\\/doc-inifcrna5003876.shtml\"]","wapurl":"https:\/\/finance.sina.cn\/usstock\/mggd\/2026-06-30\/detail-inifcrna5003876.d.html","wapurls":"[\"https:\\\/\\\/finance.sina.cn\\\/usstock\\\/mggd\\\/2026-06-30\\\/detail-inifcrna5003876.d.html\",\"http:\\\/\\\/finance.sina.cn\\\/usstock\\\/mggd\\\/2026-06-30\\\/detail-inifcrna5003876.d.html\"]","wapsummary":"","title":"\u5927\u5b97\u5546\u54c1\u7efc\u8ff0\uff1a\u6cb9\u4ef7\u4e0a\u6da8 \u4f26\u94dc\u4e0b\u6ed1 \u9ec4\u91d1\u8d70\u4f4e","stitle":"","summary":"","intro":"\u6cb9\u4ef7\u5468\u4e00\u4e0a\u6da8\u3002\u5728\u970d\u5c14\u6728\u5179\u6d77\u5ce1\u5468\u672b\u7206\u53d1\u7684\u51b2\u7a81\u518d\u6b21\u51f8\u663e\u4e2d\u4e1c\u505c\u706b\u534f\u8bae\u7684\u8106\u5f31\u6027\u540e\uff0c\u4ea4\u6613\u5458\u6b63\u5728\u8bc4\u4f30\u5373\u5c06\u4e3e\u884c\u7684\u7f8e\u4f0a\u548c\u5e73\u8c08\u5224\u524d\u666f\u3002\u94dc\u4ef7\u4e0b\u6ed1\uff0c\u9664\u7f8e\u4f0a\u548c\u8c08\u4e4b\u5916...","author":"","commentid":"cj:comos-nifcrna5003876:0","video_id":"","keywords":"","media_name":"\u73af\u7403\u5e02\u573a\u64ad\u62a5","columnid":"1840,1850,1978,2018,2032,2048","subjectid":"","img":{"u":"http:\/\/n.sinaimg.cn\/finance\/c30320b4\/20210712\/wx_poster_finance1.png","w":100,"h":100,"t":""},"images":[],"lids":"295,747,1059,1083,1084,1107,1131,1134,2509,2516,2517,2518,2519,2544,2671,2672,2676,3076,3318","oid":"869173002"},{"icons":"","is_cre_manual":"0","hqChart":"{\"stockCharts\":\"no\",\"stockCode\":\"\",\"stockMarket\":\"\",\"mulStockChart\":\"\",\"isStaticStock\":\"\"}","intime":"1782772900","channelid":"31","ctime":"1782772786","mtime":"1782772897","authoruid":"0","level":"2","vid":"0","ipad_vid":"0","video_time_length":"0","categoryid":"1","mediaid":"0","templateid":"0","productid":"0","ext_0":"0","ext_1":"0","ext_2":"0","ext_3":"0","ext_4":"0","docid":"comos:nifcrna5002364","url":"https:\/\/finance.sina.com.cn\/stock\/usstock\/c\/2026-06-30\/doc-inifcrna5002364.shtml","urls":"[\"https:\\\/\\\/finance.sina.com.cn\\\/stock\\\/usstock\\\/c\\\/2026-06-30\\\/doc-inifcrna5002364.shtml\"]","wapurl":"https:\/\/finance.sina.cn\/usstock\/mggd\/2026-06-30\/detail-inifcrna5002364.d.html","wapurls":"[\"https:\\\/\\\/finance.sina.cn\\\/usstock\\\/mggd\\\/2026-06-30\\\/detail-inifcrna5002364.d.html\",\"http:\\\/\\\/finance.sina.cn\\\/usstock\\\/mggd\\\/2026-06-30\\\/detail-inifcrna5002364.d.html\"]","wapsummary":"","title":"\u82f9\u679c\u7684\u201c\u5370\u5ea6\u68a6\u201d\u906d\u9047\u91cd\u51fb\uff1a\u6838\u5fc3\u4f9b\u5e94\u5546\u88ab\u9ed1\uff0ciPhone 18 Pro\u673a\u5bc6\u6587\u4ef6\u88ab\u6302\u6697\u7f51","stitle":"","summary":"","intro":"\u636e\u6587\u4ef6\u548c\u6d88\u606f\u4eba\u58eb\u900f\u9732\uff0c\u7a83\u53d6\u4e86\u82f9\u679c\u516c\u53f8\u5370\u5ea6\u4f9b\u5e94\u5546\u5854\u5854\u7535\u5b50\u516c\u53f8\u6570\u636e\u7684\u52d2\u7d22\u8f6f\u4ef6\u7ec4\u7ec7\u5728\u6697\u7f51\u4e0a\u53d1\u5e03\u7684\u6587\u4ef6\u4e2d\uff0c\u5305\u542b\u4e86\u82f9\u679c\u5373\u5c06\u63a8\u51fa\u7684 iPhone 18 Pro...","author":"","commentid":"cj:comos-nifcrna5002364:0","video_id":"","keywords":"","media_name":"\u73af\u7403\u5e02\u573a\u64ad\u62a5","columnid":"186312,1840,1850,2018,2032","subjectid":"","img":[],"images":[{"u":"http:\/\/n.sinaimg.cn\/finance\/transform\/132\/w550h382\/20260630\/d695-1b4c6b1bd65456de9a32d2f841d66ccd.png","w":"550","h":"382","t":""}],"lids":"295,747,1059,1083,1084,1131,1134,2431,2509,2515,2516,2517,2518,2519,2544,2671,2672,2676,3076,3318","oid":"869172222"},{"icons":"","is_cre_manual":"0","hqChart":"{\"stockCharts\":\"no\",\"stockCode\":\"\",\"stockMarket\":\"\",\"mulStockChart\":\"\",\"isStaticStock\":\"\"}","intime":"1782771931","channelid":"31","ctime":"1782771926","mtime":"1782771930","authoruid":"0","level":"2","vid":"0","ipad_vid":"0","video_time_length":"0","categoryid":"1","mediaid":"0","templateid":"0","productid":"0","ext_0":"0","ext_1":"0","ext_2":"0","ext_3":"0","ext_4":"0","docid":"comos:nifcrne1774714","url":"https:\/\/finance.sina.com.cn\/stock\/usstock\/c\/2026-06-30\/doc-inifcrne1774714.shtml","urls":"[\"https:\\\/\\\/finance.sina.com.cn\\\/stock\\\/usstock\\\/c\\\/2026-06-30\\\/doc-inifcrne1774714.shtml\"]","wapurl":"https:\/\/finance.sina.cn\/usstock\/mggd\/2026-06-30\/detail-inifcrne1774714.d.html","wapurls":"[\"https:\\\/\\\/finance.sina.cn\\\/usstock\\\/mggd\\\/2026-06-30\\\/detail-inifcrne1774714.d.html\",\"http:\\\/\\\/finance.sina.cn\\\/usstock\\\/mggd\\\/2026-06-30\\\/detail-inifcrne1774714.d.html\"]","wapsummary":"","title":"FAA\uff1a\u6377\u84dd\u822a\u7a7a\u822a\u73ed\u5728\u63a5\u8fd1\u80af\u5c3c\u8fea\u673a\u573a\u65f6\u649e\u4e0a\u65e0\u4eba\u673a","stitle":"","summary":"","intro":" \u7f8e\u56fd\u8054\u90a6\u822a\u7a7a\u7ba1\u7406\u5c40\u8868\u793a\uff0c\u5df2\u5c31\u6377\u84dd\u822a\u7a7a\u4e00\u8d9f\u822a\u73ed\u636e\u62a5\u5728\u5468\u4e00\u63a5\u8fd1\u7ebd\u7ea6\u7ea6\u7ff0\u00b7\u80af\u5c3c\u8fea\u56fd\u9645\u673a\u573a\u65f6\u649e\u4e0a\u4e00\u67b6\u65e0\u4eba\u673a\u7684\u4e8b\u4ef6\u5c55\u5f00\u8c03\u67e5\u3002","author":"","commentid":"cj:comos-nifcrne1774714:0","video_id":"0","keywords":"","media_name":"\u73af\u7403\u5e02\u573a\u64ad\u62a5","columnid":"1840,1850,2018,2032","subjectid":"","img":[],"images":[{"u":"http:\/\/n.sinaimg.cn\/finance\/transform\/116\/w550h366\/20260630\/099e-568b30bdf869ae0c217e5732a351ee97.png","w":"550","h":"366","t":""}],"lids":"295,747,1059,1083,1084,1131,1134,2509,2516,2517,2518,2519,2544,2671,2672,2676,3076,3318","oid":"869170228","mlids":"","ext":"1"},{"columnid":"1840,1850,1966,2018,2032,2048","wapurl":"https:\/\/finance.sina.cn\/usstock\/mggd\/2026-06-30\/detail-inifcrnk6776855.d.html","oid":"869167037","img":[],"subjectid":"","ipad_vid":"0","commentid":"cj:comos-nifcrnk6776855:0","vid":"0","video_id":"","channelid":"31","intime":"1782771298","video_time_length":"0","categoryid":"1","hqChart":"{\"stockCharts\":\"no\",\"stockCode\":\"\",\"stockMarket\":\"\",\"mulStockChart\":\"\",\"isStaticStock\":\"\"}","intro":"\u5168\u7403\u8d22\u7ecf\u5a92\u4f53\u6628\u591c\u4eca\u6668\u5171\u540c\u5173\u6ce8\u7684\u5934\u6761\u65b0\u95fb\u4e3b\u8981\u6709\uff1a 1\u3001\u7f8e\u8054\u50a8\u7406\u4e8b\u5e93\u514b\u6682\u65f6\u4fdd\u4f4f\u804c\u4f4d \u4f46\u6700\u9ad8\u6cd5\u9662\u6ca1\u5bf9\u7279\u6717\u666e\u5f7b\u5e95\u5173\u4e0a\u5927\u95e8 2\u3001\u4f0a\u6717\u79f0\u65e0\u8ba1\u5212\u5728\u591a\u54c8\u4e0e\u7f8e\u65b9\u4f1a\u9762...","mediaid":"0","ctime":"1782770477","is_cre_manual":"0","author":"","stitle":"","images":[{"u":"https:\/\/n.sinaimg.cn\/finance\/transform\/700\/w400h300\/20260516\/c286-2e1812752c5266fddc2fa684da88e482.jpg","w":"400","h":"300","t":""},{"u":"https:\/\/n.sinaimg.cn\/finance\/transform\/59\/w550h309\/20260630\/c8ca-2fae135cedad28aeace6c1a71ca338bf.jpg","w":"550","h":"309","t":""},{"u":"https:\/\/n.sinaimg.cn\/finance\/transform\/116\/w550h366\/20260630\/00fe-b675013a14806ae4ec597027cde04ff8.png","w":"550","h":"366","t":""},{"u":"https:\/\/n.sinaimg.cn\/finance\/transform\/114\/w550h364\/20260530\/6c2d-3aa4d2609ffe0b5f96fca76e2adec9c9.png","w":"550","h":"364","t":""},{"u":"http:\/\/n.sinaimg.cn\/finance\/transform\/148\/w474h474\/20260630\/ab49-9b7f9d05307f2ab14e83a0d067484c24.png","w":"474","h":"474","t":""},{"u":"http:\/\/n.sinaimg.cn\/finance\/transform\/116\/w550h366\/20260630\/4f92-bf2402cb27a7e894ae69efc44e4e00f2.png","w":"550","h":"366","t":""},{"u":"https:\/\/n.sinaimg.cn\/finance\/transform\/116\/w550h366\/20260630\/3df0-c44ddc5ba324eff806c92c75a63a0b51.png","w":"550","h":"366","t":""}],"keywords":"","icons":"","mtime":"1782771297","media_name":"\u73af\u7403\u5e02\u573a\u64ad\u62a5","ext_0":"0","ext_1":"0","ext_2":"0","title":"6\u670830\u65e5\u5916\u76d8\u5934\u6761\uff1a\u7f8e\u6700\u9ad8\u6cd5\u9662\u88c1\u5b9a\u7f8e\u8054\u50a8\u7406\u4e8b\u5e93\u514b\u7559\u4efb \u4f0a\u6717\u79f0\u65e0\u8ba1\u5212\u5728\u591a\u54c8\u4e0e\u7f8e\u65b9\u4f1a\u9762","ext_3":"0","docid":"comos:nifcrnk6776855","ext_4":"0","urls":"[\"https:\\\/\\\/finance.sina.com.cn\\\/stock\\\/usstock\\\/c\\\/2026-06-30\\\/doc-inifcrnk6776855.shtml\"]","templateid":"0","lids":"295,747,1059,1083,1084,1131,1134,2487,2509,2516,2517,2518,2519,2544,2671,2672,2676,3076,3318","productid":"0","wapurls":"[\"https:\\\/\\\/finance.sina.cn\\\/usstock\\\/mggd\\\/2026-06-30\\\/detail-inifcrnk6776855.d.html\",\"http:\\\/\\\/finance.sina.cn\\\/usstock\\\/mggd\\\/2026-06-30\\\/detail-inifcrnk6776855.d.html\"]","summary":"","url":"https:\/\/finance.sina.com.cn\/stock\/usstock\/c\/2026-06-30\/doc-inifcrnk6776855.shtml","authoruid":"0","wapsummary":"","level":"2"},{"icons":"","is_cre_manual":"0","hqChart":"{\"stockCharts\":\"no\",\"stockCode\":\"\",\"stockMarket\":\"\",\"mulStockChart\":\"\",\"isStaticStock\":\"\"}","intime":"1782770687","channelid":"31","ctime":"1782770178","mtime":"1782770681","authoruid":"0","level":"2","vid":"0","ipad_vid":"0","video_time_length":"0","categoryid":"1","mediaid":"0","templateid":"0","productid":"0","ext_0":"0","ext_1":"0","ext_2":"0","ext_3":"0","ext_4":"0","docid":"comos:nifcrna4988718","url":"https:\/\/finance.sina.com.cn\/stock\/usstock\/c\/2026-06-30\/doc-inifcrna4988718.shtml","urls":"[\"https:\\\/\\\/finance.sina.com.cn\\\/stock\\\/usstock\\\/c\\\/2026-06-30\\\/doc-inifcrna4988718.shtml\"]","wapurl":"https:\/\/finance.sina.cn\/usstock\/mggd\/2026-06-30\/detail-inifcrna4988718.d.html","wapurls":"[\"https:\\\/\\\/finance.sina.cn\\\/usstock\\\/mggd\\\/2026-06-30\\\/detail-inifcrna4988718.d.html\",\"http:\\\/\\\/finance.sina.cn\\\/usstock\\\/mggd\\\/2026-06-30\\\/detail-inifcrna4988718.d.html\"]","wapsummary":"","title":"\u4f0a\u6717\u79f0\u65e0\u8ba1\u5212\u5728\u591a\u54c8\u4e0e\u7f8e\u65b9\u4f1a\u9762 \u91cd\u7533\u5c06\u63a7\u5236\u970d\u5c14\u6728\u5179\u6d77\u5ce1\u901a\u884c","stitle":"","summary":"","intro":" \u4f0a\u6717\u4e00\u540d\u9ad8\u7ea7\u5b98\u5458\u91cd\u7533\uff0c\u5fb7\u9ed1\u5170\u51b3\u5fc3\u7ee7\u7eed\u63a7\u5236\u901a\u8fc7\u970d\u5c14\u6728\u5179\u6d77\u5ce1\u7684\u6d77\u4e0a\u4ea4\u901a\uff0c\u8fd9\u52a0\u5927\u4e86\u7f8e\u4f0a\u65b0\u4e00\u8f6e\u65e8\u5728\u6c38\u4e45\u7ed3\u675f\u6218\u4e89\u8c08\u5224\u7684\u538b\u529b\u3002","author":"","commentid":"cj:comos-nifcrna4988718:0","video_id":"","keywords":"","media_name":"\u73af\u7403\u5e02\u573a\u64ad\u62a5","columnid":"1840,1850,2018,2032","subjectid":"","img":[],"images":[{"u":"http:\/\/n.sinaimg.cn\/finance\/transform\/81\/w550h331\/20260630\/e0d2-881a10c64bd4f9be67ebd4e1925fcafd.png","w":"550","h":"331","t":""}],"lids":"295,747,1059,1083,1084,1131,1134,2509,2516,2517,2518,2519,2544,2671,2672,2676,3076,3318","oid":"869166549","comment_reply":0,"comment_show":0,"comment_total":0},{"icons":"","is_cre_manual":"0","hqChart":"{\"stockCharts\":\"no\",\"stockCode\":\"\",\"stockMarket\":\"\",\"mulStockChart\":\"\",\"isStaticStock\":\"\"}","intime":"1782770720","channelid":"31","ctime":"1782769788","mtime":"1782770715","authoruid":"0","level":"2","vid":"0","ipad_vid":"0","video_time_length":"0","categoryid":"1","mediaid":"0","templateid":"0","productid":"0","ext_0":"0","ext_1":"0","ext_2":"0","ext_3":"0","ext_4":"0","docid":"comos:nifcrne1764355","url":"https:\/\/finance.sina.com.cn\/stock\/usstock\/c\/2026-06-30\/doc-inifcrne1764355.shtml","urls":"[\"https:\\\/\\\/finance.sina.com.cn\\\/stock\\\/usstock\\\/c\\\/2026-06-30\\\/doc-inifcrne1764355.shtml\"]","wapurl":"https:\/\/finance.sina.cn\/usstock\/mggd\/2026-06-30\/detail-inifcrne1764355.d.html","wapurls":"[\"https:\\\/\\\/finance.sina.cn\\\/usstock\\\/mggd\\\/2026-06-30\\\/detail-inifcrne1764355.d.html\",\"http:\\\/\\\/finance.sina.cn\\\/usstock\\\/mggd\\\/2026-06-30\\\/detail-inifcrne1764355.d.html\"]","wapsummary":"","title":"\u7f8e\u4f0a\u548c\u5e73\u8c08\u5224\u4ee3\u8868\u524d\u5f80\u591a\u54c8\uff0c\u4f46\u4f1a\u6664\u80fd\u5426\u4e3e\u884c\u4ecd\u4e0d\u660e\u6717","stitle":"","summary":"","intro":" \u4f0a\u6717\u548c\u7f8e\u56fd\u8c08\u5224\u56e2\u961f\u539f\u5b9a\u672c\u5468\u5728\u591a\u54c8\u4f1a\u9762\uff0c\u4f46\u4f0a\u6717\u65b9\u9762\u8868\u793a\uff0c\u7531\u4e8e\u5468\u672b\u53cc\u65b9\u5bfc\u5f39\u4ea4\u706b\uff0c\u8003\u9a8c\u4e86\u65e8\u5728\u7ed3\u675f\u8fd9\u573a\u6301\u7eed\u56db\u4e2a\u6708\u6218\u4e89\u7684\u4e34\u65f6\u505c\u706b\u534f\u8bae\uff0c\u56e0\u6b64\u5e76\u672a\u5b89\u6392\u4f1a\u6664\u3002","author":"","commentid":"cj:comos-nifcrne1764355:0","video_id":"","keywords":"","media_name":"\u73af\u7403\u5e02\u573a\u64ad\u62a5","columnid":"1840,1850,2018,2032","subjectid":"","img":[],"images":[{"u":"https:\/\/n.sinaimg.cn\/finance\/transform\/116\/w550h366\/20260630\/00fe-b675013a14806ae4ec597027cde04ff8.png","w":"550","h":"366","t":""},{"u":"http:\/\/n.sinaimg.cn\/finance\/transform\/59\/w550h309\/20260630\/742a-5021ab721c1d2c70678a3b88da13448a.png","w":"550","h":"309","t":""}],"lids":"295,747,1059,1083,1084,1131,1134,2509,2516,2517,2518,2519,2544,2671,2672,2676,3076,3318","oid":"869165867","comment_reply":0,"comment_show":0,"comment_total":0},{"icons":"","is_cre_manual":"0","hqChart":"{\"stockCharts\":\"no\",\"stockCode\":\"\",\"stockMarket\":\"\",\"mulStockChart\":\"\",\"isStaticStock\":\"\"}","intime":"1782770805","channelid":"31","ctime":"1782768843","mtime":"1782770800","authoruid":"0","level":"2","vid":"0","ipad_vid":"0","video_time_length":"0","categoryid":"1","mediaid":"0","templateid":"0","productid":"0","ext_0":"0","ext_1":"0","ext_2":"0","ext_3":"0","ext_4":"0","docid":"comos:nifcrna4985441","url":"https:\/\/finance.sina.com.cn\/jjxw\/2026-06-30\/doc-inifcrna4985441.shtml","urls":"[\"https:\\\/\\\/finance.sina.com.cn\\\/jjxw\\\/2026-06-30\\\/doc-inifcrna4985441.shtml\"]","wapurl":"https:\/\/finance.sina.cn\/2026-06-30\/detail-inifcrna4985441.d.html","wapurls":"[\"https:\\\/\\\/finance.sina.cn\\\/2026-06-30\\\/detail-inifcrna4985441.d.html\",\"http:\\\/\\\/finance.sina.cn\\\/2026-06-30\\\/detail-inifcrna4985441.d.html\"]","wapsummary":"","title":"\u4e2d\u6b27\u8d38\u6613\u6295\u8d44\u78cb\u5546\u673a\u5236\u6b63\u5f0f\u6210\u7acb \u4e0b\u8bbe\u56db\u5927\u677f\u5757","stitle":"","summary":"","intro":"2026\u5e746\u670829\u65e5\uff0c\u5546\u52a1\u90e8\u90e8\u957f\u738b\u6587\u6d9b\u5728\u6b27\u76df\u603b\u90e8\u4e0e\u6b27\u59d4\u4f1a\u8d38\u6613\u548c\u7ecf\u6d4e\u5b89\u5168\u59d4\u5458\u8c22\u592b\u4e54\u7ef4\u5947\u5171\u540c\u4e3b\u6301\u53ec\u5f00\u4e2d\u6b27\u8d38\u6613\u6295\u8d44\u78cb\u5546\u673a\u5236\u9996\u6b21\u4f1a\u8bae\u5e76\u5728\u4f1a\u540e\u53d1\u8868\u8054\u5408\u58f0\u660e\u3002","author":"","commentid":"cj:comos-nifcrna4985441:0","video_id":"","keywords":"","media_name":"\u592e\u89c6","columnid":"1840,1850,2018,2032","subjectid":"","img":[],"images":[{"u":"http:\/\/n.sinaimg.cn\/spider20260630\/0\/w2048h1152\/20260630\/c758-8bdd6032a5e4e7c7987a1ad090a6366d.jpg","w":"2048","h":"1152","t":""},{"u":"http:\/\/n.sinaimg.cn\/spider20260630\/251\/w1600h251\/20260630\/68a7-gif5078c62b96b00131d8bed6a9c18782e9.gif","w":"1600","h":"251","t":""}],"lids":"295,747,1059,1083,1084,1131,1134,2509,2516,2517,2518,2519,2544,2671,2672,2676,3076,3318","oid":"869165068"},{"icons":"","is_cre_manual":"0","hqChart":"{\"stockCharts\":\"no\",\"stockCode\":\"\",\"stockMarket\":\"\",\"mulStockChart\":\"\",\"isStaticStock\":\"\"}","intime":"1782770731","channelid":"31","ctime":"1782768572","mtime":"1782770727","authoruid":"0","level":"2","vid":"0","ipad_vid":"0","video_time_length":"0","categoryid":"1","mediaid":"0","templateid":"0","productid":"0","ext_0":"0","ext_1":"0","ext_2":"0","ext_3":"0","ext_4":"0","docid":"comos:nifcrna4980653","url":"https:\/\/finance.sina.com.cn\/stock\/usstock\/c\/2026-06-30\/doc-inifcrna4980653.shtml","urls":"[\"https:\\\/\\\/finance.sina.com.cn\\\/stock\\\/usstock\\\/c\\\/2026-06-30\\\/doc-inifcrna4980653.shtml\"]","wapurl":"https:\/\/finance.sina.cn\/usstock\/mggd\/2026-06-30\/detail-inifcrna4980653.d.html","wapurls":"[\"https:\\\/\\\/finance.sina.cn\\\/usstock\\\/mggd\\\/2026-06-30\\\/detail-inifcrna4980653.d.html\",\"http:\\\/\\\/finance.sina.cn\\\/usstock\\\/mggd\\\/2026-06-30\\\/detail-inifcrna4980653.d.html\"]","wapsummary":"","title":"\u7f8e\u56fd3\u4e2a\u6708\u671f\u56fd\u5e93\u5238\u9700\u6c42\u964d\u81f32024\u5e74\u4ee5\u6765\u6700\u5f31\u6c34\u5e73","stitle":"","summary":"","intro":" \u5728\u7f8e\u8054\u50a8\u8d27\u5e01\u653f\u7b56\u8def\u5f84\u5b58\u5728\u4e0d\u786e\u5b9a\u6027\u3001\u4e14\u53d1\u884c\u89c4\u6a21\u589e\u81f3\u7eaa\u5f55\u9ad8\u4f4d\u4e4b\u9645\uff0c\u7f8e\u56fd\u8d22\u653f\u90e8\u5468\u4e00\u8fdb\u884c\u76843\u4e2a\u6708\u671f\u56fd\u5e93\u5238\u62cd\u5356\u9700\u6c42\u8d8b\u5f31\uff0c\u95f4\u63a5\u6295\u6807\u4eba\u83b7\u914d\u6bd4\u4f8b\u964d\u81f3\u903e\u4e00\u5e74\u534a\u4ee5\u6765\u6700\u4f4e\u3002","author":"","commentid":"cj:comos-nifcrna4980653:0","video_id":"","keywords":"","media_name":"\u73af\u7403\u5e02\u573a\u64ad\u62a5","columnid":"1840,1850,2018,2032","subjectid":"","img":{"u":"http:\/\/n.sinaimg.cn\/finance\/c30320b4\/20210712\/wx_poster_finance1.png","w":100,"h":100,"t":""},"images":[],"lids":"295,747,1059,1083,1084,1131,1134,2509,2516,2517,2518,2519,2544,2671,2672,2676,3076,3318","oid":"869163239","comment_reply":0,"comment_show":0,"comment_total":0},{"icons":"","is_cre_manual":"0","hqChart":"{\"stockCharts\":\"no\",\"stockCode\":\"\",\"stockMarket\":\"\",\"mulStockChart\":\"\",\"isStaticStock\":\"\"}","intime":"1782768546","channelid":"31","ctime":"1782768541","mtime":"1782768541","authoruid":"0","level":"2","vid":"0","ipad_vid":"0","video_time_length":"0","categoryid":"1","mediaid":"0","templateid":"0","productid":"0","ext_0":"0","ext_1":"0","ext_2":"0","ext_3":"0","ext_4":"0","docid":"comos:nifcrnn3539014","url":"https:\/\/finance.sina.com.cn\/stock\/usstock\/c\/2026-06-30\/doc-inifcrnn3539014.shtml","urls":"[\"https:\\\/\\\/finance.sina.com.cn\\\/stock\\\/usstock\\\/c\\\/2026-06-30\\\/doc-inifcrnn3539014.shtml\"]","wapurl":"https:\/\/finance.sina.cn\/usstock\/mggd\/2026-06-30\/detail-inifcrnn3539014.d.html","wapurls":"[\"https:\\\/\\\/finance.sina.cn\\\/usstock\\\/mggd\\\/2026-06-30\\\/detail-inifcrnn3539014.d.html\",\"http:\\\/\\\/finance.sina.cn\\\/usstock\\\/mggd\\\/2026-06-30\\\/detail-inifcrnn3539014.d.html\"]","wapsummary":"","title":"\u7f8e\u56fd\u80a1\u5e02\uff1a\u9022\u4f4e\u4e70\u76d8\u63a8\u52a8\u79d1\u6280\u80a1\u53cd\u5f39 \u7eb3\u65af\u8fbe\u514b100\u6307\u6570\u4e0a\u6da8\u903e2%","stitle":"","summary":"","intro":"\u9022\u4f4e\u4e70\u76d8\u5468\u4e00\u6d8c\u5165\u8fd1\u671f\u906d\u91cd\u632b\u7684\u79d1\u6280\u80a1\uff0c\u63a8\u52a8\u7f8e\u56fd\u80a1\u5e02\u4ece\u4e0a\u5468\u7684\u8dcc\u52bf\u4e2d\u53cd\u5f39\u3002 \u4ee5\u79d1\u6280\u80a1\u4e3a\u4e3b\u7684\u7eb3\u65af\u8fbe\u514b100\u6307\u6570\u5468\u4e00\u5728\u7ebd\u7ea6\u6536\u6da82.3%\uff0c\u626d\u8f6c\u4e86\u4e0a\u5468\u4e94\u7684\u8dcc\u52bf\u3002","author":"","commentid":"cj:comos-nifcrnn3539014:0","video_id":"","keywords":"","media_name":"\u73af\u7403\u5e02\u573a\u64ad\u62a5","columnid":"1840,1850,2018,2032","subjectid":"","img":{"u":"http:\/\/n.sinaimg.cn\/finance\/c30320b4\/20210712\/wx_poster_finance1.png","w":100,"h":100,"t":""},"images":[],"lids":"295,747,1059,1083,1084,1131,1134,2509,2516,2517,2518,2519,2544,2671,2672,2676,3076,3318","oid":"869163076"},{"icons":"","is_cre_manual":"0","hqChart":"{\"stockCharts\":\"no\",\"stockCode\":\"\",\"stockMarket\":\"\",\"mulStockChart\":\"\",\"isStaticStock\":\"\"}","intime":"1782768273","channelid":"31","ctime":"1782768268","mtime":"1782768268","authoruid":"0","level":"2","vid":"0","ipad_vid":"0","video_time_length":"0","categoryid":"1","mediaid":"0","templateid":"0","productid":"0","ext_0":"0","ext_1":"0","ext_2":"0","ext_3":"0","ext_4":"0","docid":"comos:nifcrna4978083","url":"https:\/\/finance.sina.com.cn\/stock\/usstock\/c\/2026-06-30\/doc-inifcrna4978083.shtml","urls":"[\"https:\\\/\\\/finance.sina.com.cn\\\/stock\\\/usstock\\\/c\\\/2026-06-30\\\/doc-inifcrna4978083.shtml\"]","wapurl":"https:\/\/finance.sina.cn\/usstock\/mggd\/2026-06-30\/detail-inifcrna4978083.d.html","wapurls":"[\"https:\\\/\\\/finance.sina.cn\\\/usstock\\\/mggd\\\/2026-06-30\\\/detail-inifcrna4978083.d.html\",\"http:\\\/\\\/finance.sina.cn\\\/usstock\\\/mggd\\\/2026-06-30\\\/detail-inifcrna4978083.d.html\"]","wapsummary":"","title":"\u6218\u706b\u672a\u65ad\u3001\u822a\u9053\u672a\u95ed\uff1a\u970d\u5c14\u6728\u5179\u6d77\u5ce1\u822a\u8fd0\u6d41\u91cf\u4ecd\u7ef4\u6301\u9ad8\u4f4d","stitle":"","summary":"","intro":" \u5728\u4e0a\u5468\u672b\u7f8e\u4f0a\u518d\u5ea6\u76f8\u4e92\u53d1\u52a8\u65b0\u88ad\u51fb\u4e4b\u540e\uff0c\u5173\u952e\u901a\u9053\u970d\u5c14\u6728\u5179\u6d77\u5ce1\u7684\u822a\u8fd0\u6d41\u91cf\u4f9d\u7136\u4fdd\u6301\u9ad8\u4f4d\uff0c\u4f3c\u4e4e\u81f3\u5c11\u5728\u4e00\u5b9a\u7a0b\u5ea6\u4e0a\u5e76\u672a\u53d7\u5230\u65f6\u65ad\u65f6\u7eed\u7684\u548c\u8c08\u5f71\u54cd\u3002","author":"","commentid":"cj:comos-nifcrna4978083:0","video_id":"","keywords":"","media_name":"\u73af\u7403\u5e02\u573a\u64ad\u62a5","columnid":"1840,1850,2018,2032","subjectid":"","img":[],"images":[{"u":"http:\/\/n.sinaimg.cn\/finance\/transform\/116\/w550h366\/20260630\/4135-9af2b6e10c41cc330953477d7ce36504.png","w":"550","h":"366","t":""},{"u":"http:\/\/n.sinaimg.cn\/finance\/transform\/203\/w550h453\/20260630\/e8f9-573fa7a51313fe3e45e01e9ea84af4a2.png","w":"550","h":"453","t":""}],"lids":"295,747,1059,1083,1084,1131,1134,2509,2516,2517,2518,2519,2544,2671,2672,2676,3076,3318","oid":"869162279"},{"icons":"","is_cre_manual":"0","hqChart":"{\"stockCharts\":\"no\",\"stockCode\":\"\",\"stockMarket\":\"\",\"mulStockChart\":\"\",\"isStaticStock\":\"\"}","intime":"1782767439","channelid":"31","ctime":"1782767435","mtime":"1782767435","authoruid":"0","level":"2","vid":"0","ipad_vid":"0","video_time_length":"0","categoryid":"1","mediaid":"0","templateid":"0","productid":"0","ext_0":"0","ext_1":"0","ext_2":"0","ext_3":"0","ext_4":"0","docid":"comos:nifcmeh1878783","url":"https:\/\/finance.sina.com.cn\/stock\/usstock\/c\/2026-06-30\/doc-inifcmeh1878783.shtml","urls":"[\"https:\\\/\\\/finance.sina.com.cn\\\/stock\\\/usstock\\\/c\\\/2026-06-30\\\/doc-inifcmeh1878783.shtml\"]","wapurl":"https:\/\/finance.sina.cn\/usstock\/mggd\/2026-06-30\/detail-inifcmeh1878783.d.html","wapurls":"[\"https:\\\/\\\/finance.sina.cn\\\/usstock\\\/mggd\\\/2026-06-30\\\/detail-inifcmeh1878783.d.html\",\"http:\\\/\\\/finance.sina.cn\\\/usstock\\\/mggd\\\/2026-06-30\\\/detail-inifcmeh1878783.d.html\"]","wapsummary":"","title":"Alphabet \u9053\u6307\u9996\u79c0\u4e2d\u4e0a\u6da84%","stitle":"","summary":"","intro":"Alphabet \u80a1\u4ef7\u5468\u4e00\u4e0a\u6da8 4%\uff0c\u8be5\u516c\u53f8\u6b63\u5f0f\u52a0\u5165\u9053\u743c\u65af\u5de5\u4e1a\u5e73\u5747\u6307\u6570\uff0c\u53d6\u4ee3\u4e86Verizon \uff0c\u5e76\u88ab\u8d4b\u4e88\u84dd\u7b79\u80a1\u7684\u8c61\u5f81\u6027\u79f0\u53f7\u3002 \u5c3d\u7ba1\u80a1\u4ef7\u5468\u4e00\u53cd\u5f39\uff0c\u4f46\u538b\u529b\u4f9d\u7136\u5b58\u5728\u3002","author":"","commentid":"cj:comos-nifcmeh1878783:0","video_id":"0","keywords":"","media_name":"\u73af\u7403\u5e02\u573a\u64ad\u62a5","columnid":"1840,1850,2018,2032","subjectid":"","img":[],"images":[{"u":"http:\/\/n.sinaimg.cn\/finance\/transform\/390\/w550h640\/20260630\/f402-3494ffd4e6841d042d3402d7a7d5570c.jpg","w":"550","h":"640","t":""}],"lids":"295,747,1059,1083,1084,1131,1134,2509,2516,2517,2518,2519,2544,2671,2672,2676,3076,3318","oid":"869159797","mlids":"","ext":"1"},{"icons":"","is_cre_manual":"0","hqChart":"{\"stockCharts\":\"\\u7f8e\\u80a1\\u5206\\u65f6\\u56fe\",\"stockCode\":\"\",\"stockMarket\":\"us\",\"mulStockChart\":\"\",\"isStaticStock\":\"\"}","intime":"1782771292","channelid":"31","ctime":"1782766862","mtime":"1782771292","authoruid":"0","level":"1","vid":"0","ipad_vid":"0","video_time_length":"0","categoryid":"1","mediaid":"0","templateid":"0","productid":"0","ext_0":"0","ext_1":"0","ext_2":"0","ext_3":"0","ext_4":"0","docid":"comos:nifcmen6876783","url":"https:\/\/finance.sina.com.cn\/stock\/usstock\/c\/2026-06-30\/doc-inifcmen6876783.shtml","urls":"[\"https:\\\/\\\/finance.sina.com.cn\\\/stock\\\/usstock\\\/c\\\/2026-06-30\\\/doc-inifcmen6876783.shtml\"]","wapurl":"https:\/\/finance.sina.cn\/usstock\/mggd\/2026-06-30\/detail-inifcmen6876783.d.html","wapurls":"[\"https:\\\/\\\/finance.sina.cn\\\/usstock\\\/mggd\\\/2026-06-30\\\/detail-inifcmen6876783.d.html\",\"http:\\\/\\\/finance.sina.cn\\\/usstock\\\/mggd\\\/2026-06-30\\\/detail-inifcmen6876783.d.html\"]","wapsummary":"","title":"6\u670830\u65e5\u7f8e\u80a1\u6210\u4ea4\u989d\u524d20\uff1a\u745e\u94f6\u4e0a\u8c03\u53f0\u79ef\u7535\u76ee\u6807\u4ef7","stitle":"","summary":"","intro":"\u5468\u4e00\u7f8e\u80a1\u6210\u4ea4\u989d\u7b2c1\u540d\u7f8e\u5149\u79d1\u6280\u6536\u9ad81.14%\uff0c\u6210\u4ea4659.15\u4ebf\u7f8e\u5143\u3002\u65e5\u524d\u7f8e\u5149\u4e0e\u82f9\u679c\u5c31\u5b58\u50a8\u82af\u7247\u5b9a\u4ef7\u95ee\u9898\u516c\u5f00\u4ea4\u950b\u3002\u7f8e\u5149CEO\u6851\u6770\u00b7\u6885\u8d6b\u7f57\u7279\u62c9\u79f0\uff0c\u82f9\u679c\u5341\u591a\u5e74\u6765\u4ee55\u7f8e\u5143\u91c7\u8d2d\u82af\u7247...","author":"","commentid":"cj:comos-nifcmen6876783:0","video_id":"","keywords":"","media_name":"\u73af\u7403\u5e02\u573a\u64ad\u62a5","columnid":"1850,2018,2032","subjectid":"","img":[],"images":[{"u":"https:\/\/n.sinaimg.cn\/tech\/transform\/520\/w550h2370\/20260630\/33eb-f2b1182140de4e35e17369b71407cf19.png","w":"550","h":"2370","t":""}],"lids":"295,747,1083,1084,1131,1134,2509,2516,2517,2518,2519,2544,2671,2672,2676,3318","oid":"869158108","comment_reply":0,"comment_show":0,"comment_total":0},{"icons":"","is_cre_manual":"0","hqChart":"{\"stockCharts\":\"no\",\"stockCode\":\"\",\"stockMarket\":\"\",\"mulStockChart\":\"\",\"isStaticStock\":\"\"}","intime":"1782768726","channelid":"31","ctime":"1782766052","mtime":"1782768721","authoruid":"0","level":"2","vid":"0","ipad_vid":"0","video_time_length":"0","categoryid":"1","mediaid":"0","templateid":"0","productid":"0","ext_0":"0","ext_1":"0","ext_2":"0","ext_3":"0","ext_4":"0","docid":"comos:nifcmeq3647214","url":"https:\/\/finance.sina.com.cn\/stock\/usstock\/c\/2026-06-30\/doc-inifcmeq3647214.shtml","urls":"[\"https:\\\/\\\/finance.sina.com.cn\\\/stock\\\/usstock\\\/c\\\/2026-06-30\\\/doc-inifcmeq3647214.shtml\"]","wapurl":"https:\/\/finance.sina.cn\/usstock\/mggd\/2026-06-30\/detail-inifcmeq3647214.d.html","wapurls":"[\"https:\\\/\\\/finance.sina.cn\\\/usstock\\\/mggd\\\/2026-06-30\\\/detail-inifcmeq3647214.d.html\",\"http:\\\/\\\/finance.sina.cn\\\/usstock\\\/mggd\\\/2026-06-30\\\/detail-inifcmeq3647214.d.html\"]","wapsummary":"","title":"\u7f8e\u56fd\u6218\u7565\u77f3\u6cb9\u50a8\u5907\u5e93\u5b58\u51cf\u5c11550\u4e07\u6876\uff0c\u964d\u81f31983\u5e74\u4ee5\u6765\u6700\u4f4e\u6c34\u5e73","stitle":"","summary":"","intro":" \u636e\u7f8e\u56fd\u80fd\u6e90\u90e8\u6570\u636e\uff0c\u7f8e\u56fd\u6218\u7565\u77f3\u6cb9\u50a8\u5907\uff08SPR\uff09\u4e2d\u7684\u539f\u6cb9\u5e93\u5b58\u51cf\u5c11\u4e86550\u4e07\u6876\uff0c\u964d\u81f33.257\u4ebf\u6876\uff0c\u521b\u4e0b\u81ea1983\u5e745\u6708\u4ee5\u6765\u7684\u6700\u4f4e\u6c34\u5e73\u3002","author":"","commentid":"cj:comos-nifcmeq3647214:0","video_id":"","keywords":"","media_name":"\u73af\u7403\u5e02\u573a\u64ad\u62a5","columnid":"1840,1850,1978,2018,2032","subjectid":"","img":[],"images":[{"u":"http:\/\/n.sinaimg.cn\/finance\/transform\/116\/w550h366\/20260630\/3df0-c44ddc5ba324eff806c92c75a63a0b51.png","w":"550","h":"366","t":""}],"lids":"295,747,1059,1083,1084,1107,1131,1134,2509,2516,2517,2518,2519,2544,2671,2672,2676,3076,3318","oid":"869156789","mlids":"","ext":"1"},{"icons":"","is_cre_manual":"0","hqChart":"{\"stockCharts\":\"\\u7f8e\\u80a1\\u5206\\u65f6\\u56fe\",\"stockCode\":\"\",\"stockMarket\":\"us\",\"mulStockChart\":\"\",\"isStaticStock\":\"\"}","intime":"1782765872","channelid":"31","ctime":"1782765869","mtime":"1782765871","authoruid":"0","level":"1","vid":"0","ipad_vid":"0","video_time_length":"0","categoryid":"1","mediaid":"0","templateid":"0","productid":"0","ext_0":"0","ext_1":"0","ext_2":"0","ext_3":"0","ext_4":"0","docid":"comos:nifcmee5092352","url":"https:\/\/finance.sina.com.cn\/stock\/usstock\/c\/2026-06-30\/doc-inifcmee5092352.shtml","urls":"[\"https:\\\/\\\/finance.sina.com.cn\\\/stock\\\/usstock\\\/c\\\/2026-06-30\\\/doc-inifcmee5092352.shtml\"]","wapurl":"https:\/\/finance.sina.cn\/usstock\/mggd\/2026-06-30\/detail-inifcmee5092352.d.html","wapurls":"[\"https:\\\/\\\/finance.sina.cn\\\/usstock\\\/mggd\\\/2026-06-30\\\/detail-inifcmee5092352.d.html\",\"http:\\\/\\\/finance.sina.cn\\\/usstock\\\/mggd\\\/2026-06-30\\\/detail-inifcmee5092352.d.html\"]","wapsummary":"","title":"\u7279\u65af\u62c9\u5373\u5c06\u53d1\u5e03\u7b2c\u4e8c\u5b63\u5ea6\u4ea4\u4ed8\u6570\u636e \u8fd9\u4e00\u5173\u952e\u6570\u5b57\u5907\u53d7\u5173\u6ce8","stitle":"","summary":"","intro":"\u7279\u65af\u62c9\u5c06\u57287\u6708\u521d\u516c\u5e03\u7b2c\u4e8c\u5b63\u5ea6\u8f66\u8f86\u4ea4\u4ed8\u6570\u636e\uff0c\u8fd9\u4e00\u6570\u5b57\u53ef\u80fd\u6bd4\u4efb\u4f55\u81ea\u52a8\u9a7e\u9a76\u51fa\u79df\u8f66\u6216\u4eba\u5f62\u673a\u5668\u4eba\u7684\u6700\u65b0\u8fdb\u5c55\u90fd\u66f4\u53d7\u5e02\u573a\u5173\u6ce8\u3002\u4ea4\u4ed8\u91cf\u662f\u8861\u91cf\u7279\u65af\u62c9\u6c7d\u8f66\u9700\u6c42\u662f\u5426\u4ece\u8270\u96be\u76842025\u5e74\u4e2d\u590d...","author":"","commentid":"cj:comos-nifcmee5092352:0","video_id":"","keywords":"","media_name":"\u73af\u7403\u5e02\u573a\u64ad\u62a5","columnid":"1850,2018,2032","subjectid":"","img":{"u":"http:\/\/n.sinaimg.cn\/finance\/c30320b4\/20210712\/wx_poster_finance1.png","w":100,"h":100,"t":""},"images":[],"lids":"295,747,1083,1084,1131,1134,2509,2516,2517,2518,2519,2544,2671,2672,2676,3318","oid":"869156392"}]}}