{"result":{"status":{"code":0,"msg":"succ"},"timestamp":"Fri Jun 26 19:45:11 +0800 2026","top":[],"pdps":[],"cre":[],"total":101306,"end":1782473118,"start":1782474264,"lid":2509,"rtime":1782474311,"data":[{"icons":"","is_cre_manual":"0","hqChart":"{\"stockCharts\":\"no\",\"stockCode\":\"\",\"stockMarket\":\"\",\"mulStockChart\":\"\",\"isStaticStock\":\"\"}","intime":"1782474269","channelid":"31","ctime":"1782474264","mtime":"1782474264","authoruid":"0","level":"2","vid":"0","ipad_vid":"0","video_time_length":"0","categoryid":"1","mediaid":"0","templateid":"0","productid":"0","ext_0":"0","ext_1":"0","ext_2":"0","ext_3":"0","ext_4":"0","docid":"comos:nietwvq5131708","url":"https:\/\/finance.sina.com.cn\/stock\/usstock\/c\/2026-06-26\/doc-inietwvq5131708.shtml","urls":"[\"https:\\\/\\\/finance.sina.com.cn\\\/stock\\\/usstock\\\/c\\\/2026-06-26\\\/doc-inietwvq5131708.shtml\"]","wapurl":"https:\/\/finance.sina.cn\/usstock\/mggd\/2026-06-26\/detail-inietwvq5131708.d.html","wapurls":"[\"https:\\\/\\\/finance.sina.cn\\\/usstock\\\/mggd\\\/2026-06-26\\\/detail-inietwvq5131708.d.html\",\"http:\\\/\\\/finance.sina.cn\\\/usstock\\\/mggd\\\/2026-06-26\\\/detail-inietwvq5131708.d.html\"]","wapsummary":"","title":"\u5927\u4f17\u6c7d\u8f66\u8ba1\u5212\u88c1\u545815% \u5e76\u5173\u95ed\u5fb7\u56fd\u56db\u5bb6\u5de5\u5382","stitle":"","summary":"","intro":"\u6838\u5fc3\u8981\u70b9 \u636e\u62a5\u9053\uff0c\u6c7d\u8f66\u5de8\u5934\u5927\u4f17\u6c7d\u8f66\u8ba1\u5212\u5728\u672a\u6765\u6570\u5e74\u88c1\u5458 10 \u4e07\u4eba\uff0c\u5e76\u5173\u505c\u5fb7\u56fd\u56db\u5bb6\u5de5\u5382\u3002 \u6b64\u6b21\u8c03\u6574\u662f\u8fd9\u5bb6\u4f01\u4e1a\u6210\u7acb 89 \u5e74\u4ee5\u6765\u89c4\u6a21\u6700\u5927\u7684\u4e00\u6b21\u6fc0\u8fdb\u6539\u9769\u3002","author":"","commentid":"cj:comos-nietwvq5131708:0","video_id":"","keywords":"","media_name":"\u73af\u7403\u5e02\u573a\u64ad\u62a5","columnid":"1850,2018,2032","subjectid":"","img":[],"images":[{"u":"http:\/\/n.sinaimg.cn\/tech\/transform\/59\/w550h309\/20260626\/7862-a2e8774d4f3f6d9b6f840329ef923d56.png","w":"550","h":"309","t":"2026 \u5e74 3 \u6708 4 \u65e5\u5468\u4e09\uff0c\u5fb7\u56fd\u6c49\u8bfa\u5a01\u7684\u5927\u4f17\u5546\u7528\u8f66\u5de5\u5382\u4e3e\u529e\u5a92\u4f53\u5f00\u653e\u65e5\u6d3b\u52a8\uff0c\u5de5\u4f5c\u4eba\u5458\u6b63\u5728\u4e3a\u5927\u4f17 ID.Buzz \u7535\u52a8\u53a2\u5f0f\u8f66\u5b89\u88c5\u81ea\u52a8\u9a7e\u9a76\u6fc0\u5149\u96f7\u8fbe\u7cfb\u7edf\u3002"}],"lids":"295,747,1083,1084,1131,1134,2509,2516,2517,2518,2519,2544,2671,2672,2676,3318","oid":"868299823"},{"icons":"","is_cre_manual":"0","hqChart":"{\"stockCharts\":\"no\",\"stockCode\":\"\",\"stockMarket\":\"\",\"mulStockChart\":\"\",\"isStaticStock\":\"\"}","intime":"1782474297","channelid":"31","ctime":"1782474191","mtime":"1782474290","authoruid":"0","level":"2","vid":"0","ipad_vid":"0","video_time_length":"0","categoryid":"1","mediaid":"0","columnid":"1921","templateid":"0","productid":"0","ext_0":"0","ext_1":"0","ext_2":"0","ext_3":"0","ext_4":"0","docid":"comos:nietwvq5132055","url":"https:\/\/finance.sina.com.cn\/money\/bank\/bank_yhfg\/2026-06-26\/doc-inietwvq5132055.shtml","urls":"[\"https:\\\/\\\/finance.sina.com.cn\\\/money\\\/bank\\\/bank_yhfg\\\/2026-06-26\\\/doc-inietwvq5132055.shtml\"]","wapurl":"https:\/\/finance.sina.cn\/bank\/jgdt\/2026-06-26\/detail-inietwvq5132055.d.html","wapurls":"[\"https:\\\/\\\/finance.sina.cn\\\/bank\\\/jgdt\\\/2026-06-26\\\/detail-inietwvq5132055.d.html\",\"http:\\\/\\\/finance.sina.cn\\\/bank\\\/jgdt\\\/2026-06-26\\\/detail-inietwvq5132055.d.html\"]","wapsummary":"","title":"\u592e\u884c\u5c31\u540c\u4e1a\u5b58\u5355\u7ba1\u7406\u529e\u6cd5\u516c\u5f00\u5f81\u6c42\u610f\u89c1\uff0c\u62df\u589e\u52a0DR\u7b49\u4f5c\u4e3a\u5b9a\u4ef7\u53c2\u8003","stitle":"","summary":"","intro":"\u4e2d\u56fd\u4eba\u6c11\u94f6\u884c6\u670826\u65e5\u6d88\u606f\uff0c\u4e3a\u8fdb\u4e00\u6b65\u89c4\u8303\u5f15\u5bfc\u540c\u4e1a\u5b58\u5355\u5e02\u573a\u53d1\u5c55\uff0c\u52a0\u5f3a\u91d1\u878d\u76d1\u7ba1\uff0c\u4e2d\u56fd\u4eba\u6c11\u94f6\u884c\u5bf9\u300a\u540c\u4e1a\u5b58\u5355\u7ba1\u7406\u6682\u884c\u529e\u6cd5\u300b\uff08\u4ee5\u4e0b\u7b80\u79f0\u300a\u6682\u884c\u529e\u6cd5\u300b\uff09...","author":"","commentid":"cj:comos-nietwvq5132055:0","video_id":"","keywords":"","media_name":"\u4e2d\u8bc1\u91d1\u725b\u5ea7","subjectid":"","img":[],"images":[],"lids":"295,2509,2519,2544,3318","oid":"868299860"},{"icons":"","is_cre_manual":"0","hqChart":"{\"stockCharts\":\"no\",\"stockCode\":\"\",\"stockMarket\":\"\",\"mulStockChart\":\"\",\"isStaticStock\":\"\"}","intime":"1782474254","channelid":"31","ctime":"1782474180","mtime":"1782474249","authoruid":"0","level":"2","vid":"0","ipad_vid":"0","video_time_length":"0","categoryid":"1","mediaid":"0","templateid":"0","productid":"0","ext_0":"0","ext_1":"0","ext_2":"0","ext_3":"0","ext_4":"0","docid":"comos:nietwvs1907638","url":"https:\/\/finance.sina.com.cn\/jryx\/hm\/2026-06-26\/doc-inietwvs1907638.shtml","urls":"[\"https:\\\/\\\/finance.sina.com.cn\\\/jryx\\\/hm\\\/2026-06-26\\\/doc-inietwvs1907638.shtml\"]","wapurl":"https:\/\/finance.sina.cn\/2026-06-26\/detail-inietwvs1907638.d.html","wapurls":"[\"https:\\\/\\\/finance.sina.cn\\\/2026-06-26\\\/detail-inietwvs1907638.d.html\",\"http:\\\/\\\/finance.sina.cn\\\/2026-06-26\\\/detail-inietwvs1907638.d.html\"]","wapsummary":"","title":"\u90ae\u50a8\u94f6\u884c\uff1a\u72ec\u7acb\u975e\u6267\u884c\u8463\u4e8b\u6e29\u94c1\u519b\u3001\u6f58\u82f1\u4e3d\u4efb\u671f\u5c4a\u6ee1\u79bb\u4efb","stitle":"","summary":"","intro":" 6\u670826\u65e5\u91d1\u878d\u4e00\u7ebf\u6d88\u606f\uff0c\u90ae\u50a8\u94f6\u884c\u53d1\u5e03\u516c\u544a\uff0c\u72ec\u7acb\u975e\u6267\u884c\u8463\u4e8b\u6e29\u94c1\u519b\u3001\u6f58\u82f1\u4e3d\u56e0\u4efb\u671f\u5c4a\u6ee1\uff0c\u81ea2026\u5e746\u670830\u65e5\u8d77\u4e0d\u518d\u62c5\u4efb\u672c\u884c\u72ec\u7acb\u975e\u6267\u884c\u8463\u4e8b\u804c\u52a1\u3002","author":"","commentid":"cj:comos-nietwvs1907638:0","video_id":"","keywords":"","media_name":"\u91d1\u878d\u4e00\u7ebf","columnid":"1921,1924","subjectid":"","img":[],"images":[{"u":"http:\/\/n.sinaimg.cn\/finance\/transform\/568\/w550h818\/20260626\/a93e-9828a17308ec5badeb8efc1a3f461dab.png","w":"550","h":"818","t":""}],"lids":"295,2509,2519,2544,3318","oid":"868299804"},{"icons":"","is_cre_manual":"0","hqChart":"{\"stockCharts\":\"no\",\"stockCode\":\"\",\"stockMarket\":\"\",\"mulStockChart\":\"\",\"isStaticStock\":\"\"}","intime":"1782474175","channelid":"31","ctime":"1782474168","mtime":"1782474174","authoruid":"0","level":"2","vid":"0","ipad_vid":"0","video_time_length":"0","categoryid":"1","mediaid":"0","templateid":"0","productid":"0","ext_0":"0","ext_1":"0","ext_2":"0","ext_3":"0","ext_4":"0","docid":"comos:nietwvk0443500","url":"https:\/\/finance.sina.com.cn\/tech\/it\/2026-06-26\/doc-inietwvk0443500.shtml","urls":"[\"https:\\\/\\\/finance.sina.com.cn\\\/tech\\\/it\\\/2026-06-26\\\/doc-inietwvk0443500.shtml\"]","wapurl":"https:\/\/finance.sina.cn\/chanjing\/gsxw\/2026-06-26\/detail-inietwvk0443500.d.html","wapurls":"[\"https:\\\/\\\/finance.sina.cn\\\/chanjing\\\/gsxw\\\/2026-06-26\\\/detail-inietwvk0443500.d.html\",\"http:\\\/\\\/finance.sina.cn\\\/chanjing\\\/gsxw\\\/2026-06-26\\\/detail-inietwvk0443500.d.html\"]","wapsummary":"","title":"\u4e2d\u79d1\u95fb\u6b4c\u767b\u9646\u6e2f\u4ea4\u6240\uff0c\u4e0a\u5e02\u9996\u65e5\u76d8\u4e2d\u6700\u9ad8\u6da8\u5e45\u8d85105%","stitle":"","summary":"","intro":"\u65b0\u6d6a\u79d1\u6280\u8baf 6\u670826\u65e5\u665a\u95f4\u6d88\u606f\uff0c\u4eca\u65e5\uff0c\u5317\u4eac\u4e2d\u79d1\u95fb\u6b4c\u79d1\u6280\u80a1\u4efd\u6709\u9650\u516c\u53f8\uff08\u4ee5\u4e0b\u7b80\u79f0\u201c\u4e2d\u79d1\u95fb\u6b4c\u201d\uff09\u6b63\u5f0f\u767b\u9646\u6e2f\u4ea4\u6240\uff0c\u80a1\u7968\u4ee3\u78011956.HK\u3002\u516c\u53f8\u4e0a\u5e02\u9996\u65e5\u8868\u73b0\u4eae\u773c...","author":"","commentid":"cj:comos-nietwvk0443500:0","video_id":"","keywords":"","media_name":"\u65b0\u6d6a\u79d1\u6280","columnid":"186312,1908,1913","subjectid":"","img":[],"images":[{"u":"http:\/\/n.sinaimg.cn\/finance\/transform\/116\/w550h366\/20260626\/8b04-e7471179ffe088bba9801d98c4f78fa3.jpg","w":"550","h":"366","t":""}],"lids":"295,1081,1693,1694,2431,2509,2515,2516,2519,2544,3318","oid":"868299636"},{"icons":"","is_cre_manual":"0","hqChart":"{\"stockCharts\":\"no\",\"stockCode\":\"DINIW\",\"stockMarket\":\"\",\"mulStockChart\":\"\",\"isStaticStock\":\"\"}","intime":"1782474173","channelid":"31","ctime":"1782474164","mtime":"1782474172","authoruid":"0","level":"2","vid":"0","ipad_vid":"0","video_time_length":"0","categoryid":"1","mediaid":"0","templateid":"0","productid":"0","ext_0":"0","ext_1":"0","ext_2":"0","ext_3":"0","ext_4":"0","docid":"comos:nietwvk0443432","url":"https:\/\/finance.sina.com.cn\/money\/forex\/forexfxyc\/2026-06-26\/doc-inietwvk0443432.shtml","urls":"[\"https:\\\/\\\/finance.sina.com.cn\\\/money\\\/forex\\\/forexfxyc\\\/2026-06-26\\\/doc-inietwvk0443432.shtml\"]","wapurl":"https:\/\/finance.sina.cn\/forex\/hsxw\/2026-06-26\/detail-inietwvk0443432.d.html","wapurls":"[\"https:\\\/\\\/finance.sina.cn\\\/forex\\\/hsxw\\\/2026-06-26\\\/detail-inietwvk0443432.d.html\",\"http:\\\/\\\/finance.sina.cn\\\/forex\\\/hsxw\\\/2026-06-26\\\/detail-inietwvk0443432.d.html\"]","wapsummary":"\u7ebd\u7ea6\u8054\u50a8\u4e3b\u5e2d\u7ea6\u7ff0\u00b7\u5a01\u5ec9\u59c6\u65af\u5728\u5468\u56db\u91ca\u653e\u51fa\u660e\u786e\u5224\u65ad\uff1a\u7f8e\u56fd","title":"\u90a6\u8fbe\u4e9a\u6d32:\u7f8e\u5143\u56de\u843d\u6cb9\u4ef7\u53cd\u5f39 \u7f8e\u5143\u52a0\u5143\u627f\u538b\u6536\u8dcc","stitle":"","summary":"","intro":"6\u670826\u65e5\uff0c\u7ebd\u7ea6\u8054\u50a8\u4e3b\u5e2d\u7ea6\u7ff0\u00b7\u5a01\u5ec9\u59c6\u65af\u5728\u5468\u56db\u91ca\u653e\u51fa\u660e\u786e\u5224\u65ad\uff1a\u7f8e\u56fd\u5f53\u524d\u7684\u901a\u80c0\u6c34\u5e73\u4ecd\u660e\u663e\u9ad8\u4e8e\u76ee\u6807\uff0c\u5c3d\u7ba1\u672a\u6765\u51e0\u4e2a\u5b63\u5ea6\u53ef\u80fd\u51fa\u73b0\u7f13\u89e3\uff0c\u4f46\u56de\u843d\u81f32%\u7684\u8fc7\u7a0b\u5c06\u6bd4\u6b64\u524d\u9884\u671f\u66f4\u4e3a\u6f2b\u957f\u3002","author":"","commentid":"cj:comos-nietwvk0443432:0","video_id":"","keywords":"\u7f8e\u8054\u50a8,\u7f8e\u56fd","media_name":"\u5e02\u573a\u8d44\u8baf","columnid":"1966,1971,1972,1974","subjectid":"","img":[],"images":[],"lids":"295,1084,2487,2509,2519,2544,2676,3318","oid":"868299623"},{"hqChart":"{\"stockCharts\":\"no\",\"stockCode\":\"\",\"stockMarket\":\"\",\"mulStockChart\":\"\",\"isStaticStock\":\"\"}","categoryid":"1","intro":"\u51fa\u54c1\uff1a\u65b0\u6d6a\u8d22\u7ecf\u4e0a\u5e02\u516c\u53f8\u7814\u7a76\u9662\/\u6e2f\u5e02\u591a\u7ef4\u955c \u4f5c\u8005\uff1a\u559c\u4e50 \u5728AI\u7b97\u529b\u9700\u6c42\u7206\u53d1\u5f0f\u589e\u957f\u7684\u6d6a\u6f6e\u4e2d\uff0c\u5149\u6a21\u5757\u4f5c\u4e3a\u6570\u636e\u4e2d\u5fc3\u9ad8\u901f\u4e92\u8054\u7684\u6838\u5fc3\u5668\u4ef6\uff0c\u5df2\u6210\u4e3aA\u80a1\u548c\u6e2f\u80a1\u5e02\u573a\u6700\u7099\u624b\u53ef\u70ed\u7684\u8d5b\u9053\u4e4b\u4e00...","mediaid":"0","summary":"","wapurls":"[\"https:\\\/\\\/finance.sina.cn\\\/stock\\\/ssgs\\\/2026-06-26\\\/detail-inietwvq5128101.d.html\",\"http:\\\/\\\/finance.sina.cn\\\/stock\\\/ssgs\\\/2026-06-26\\\/detail-inietwvq5128101.d.html\"]","productid":"0","is_cre_manual":"0","ctime":"1782474015","author":"","url":"https:\/\/finance.sina.com.cn\/stock\/observe\/2026-06-26\/doc-inietwvq5128101.shtml","stitle":"","authoruid":"0","wapsummary":"","level":"2","columnid":"1850,1884,2000","wapurl":"https:\/\/finance.sina.cn\/stock\/ssgs\/2026-06-26\/detail-inietwvq5128101.d.html","oid":"868298915","img":[],"subjectid":"","ipad_vid":"0","commentid":"cj:comos-nietwvq5128101:0","vid":"0","video_id":"","channelid":"31","intime":"1782474020","video_time_length":"0","images":[{"u":"https:\/\/n.sinaimg.cn\/finance\/498\/w957h341\/20260626\/e726-1b9cc443520a72611759e9bcf3884166.png","w":"957","h":"341","t":""},{"u":"https:\/\/n.sinaimg.cn\/finance\/414\/w950h264\/20260626\/10e0-9ae8c4834967a26a82a010e4ec61ed19.png","w":"950","h":"264","t":""},{"u":"https:\/\/n.sinaimg.cn\/finance\/418\/w970h248\/20260626\/734d-450ceb338a37d2c926f8565f43d300ab.png","w":"970","h":"248","t":""},{"u":"https:\/\/n.sinaimg.cn\/finance\/354\/w972h182\/20260626\/7335-068b793974b026c534569c72df9b3bae.png","w":"972","h":"182","t":""},{"u":"https:\/\/n.sinaimg.cn\/finance\/303\/w809h294\/20260626\/ddd7-da509ddddc29928b0aefd44a6a772204.png","w":"809","h":"294","t":""}],"keywords":"","icons":"","mtime":"1782474015","media_name":"\u65b0\u6d6a\u8bc1\u5238","ext_0":"0","ext_1":"0","ext_2":"0","title":"\u6d77\u5149\u82af\u6b63\u6e2f\u80a1\u4e0a\u5e02\u5728\u5373\uff1a\u8e29\u4e2dAI\u5149\u6a21\u5757\u98ce\u53e3\u00a0\u8425\u6536\u4e24\u5e74\u6da8\u4e03\u500d\u00a0\u4f46JDM\u6a21\u5f0f\u96be\u589e\u5229 \u4f30\u503c\u5bf9\u6807\u5934\u90e8\u4f01\u4e1a\u6216\u6b20\u5e95\u6c14","ext_3":"0","docid":"comos:nietwvq5128101","ext_4":"0","urls":"[\"https:\\\/\\\/finance.sina.com.cn\\\/stock\\\/observe\\\/2026-06-26\\\/doc-inietwvq5128101.shtml\"]","templateid":"0","lids":"295,746,751,2509,2516,2517,2519,2544,2671,2674,3318"},{"columnid":"349,354,16692","wapurl":"https:\/\/finance.sina.cn\/tech\/2026-06-26\/detail-inietwvm7214086.d.html","oid":"868296938","img":{"u":"http:\/\/n.sinaimg.cn\/tech\/transform\/691\/w415h276\/20260626\/2d6d-074a103508e21a6d3d1f6b7bc22943a9.jpg","w":"415","h":"276","t":""},"subjectid":"","ipad_vid":"0","commentid":"kj:comos-nietwvm7214086:0","vid":"0","video_id":"","channelid":"2","intime":"1782473704","video_time_length":"0","categoryid":"1","intro":"2026\u5e74\uff0c\u5927\u6a21\u578b\u6b63\u5728\u63a5\u7ba1\u4e00\u5207\u3002 \u5199\u4ee3\u7801\u3001\u505a\u8bbe\u8ba1\u3001\u8f85\u52a9\u9a7e\u9a76\u2026\u2026AI\u7684\u8fb9\u754c\u6bcf\u5929\u90fd\u5728\u88ab\u7a81\u7834\u3002\u5728\u80fd\u6e90\u9886\u57df\uff0c\u201c\u8ba9AI\u7ba1\u7406\u5bb6\u5ead\u7535\u7f51\u201d\u4e5f\u6210\u4e86\u6700\u70ed\u95e8\u7684\u6982\u5ff5\u4e4b\u4e00\u3002","mediaid":"0","ctime":"1782473692","author":"","stitle":"","images":[{"u":"http:\/\/n.sinaimg.cn\/tech\/transform\/691\/w415h276\/20260626\/2d6d-074a103508e21a6d3d1f6b7bc22943a9.jpg","w":"415","h":"276","t":""},{"u":"http:\/\/n.sinaimg.cn\/tech\/transform\/249\/w630h419\/20260626\/8916-324faeff68357e3f191649a7659abc39.jpg","w":"630","h":"419","t":""},{"u":"http:\/\/n.sinaimg.cn\/tech\/transform\/615\/w416h199\/20260626\/89dc-b1d133eadc8a0993924a1c917abbf16a.jpg","w":"416","h":"199","t":""},{"u":"http:\/\/n.sinaimg.cn\/tech\/transform\/249\/w630h419\/20260626\/a16f-800da0f609f715f6bb71e858925bad66.jpg","w":"630","h":"419","t":""},{"u":"http:\/\/n.sinaimg.cn\/tech\/transform\/249\/w630h419\/20260626\/de3e-d928f8a3ec3e07e9d853e9e797a10646.jpg","w":"630","h":"419","t":""}],"keywords":"AI\u667a\u80fd","mtime":"1782473703","ext_0":"0","media_name":"\u65b0\u6d6a\u79d1\u6280\u7efc\u5408","ext_1":"0","ext_2":"0","title":"AI\u667a\u80fd\u4f53\u8fdb\u5165\u80fd\u6e90\u884c\u4e1a\uff0c\u6b63\u6d69EcoFlow\u5148\u5212\u51fa\u5b89\u5168\u8fb9\u754c","ext_3":"0","docid":"comos:nietwvm7214086","ext_4":"0","urls":"[\"https:\\\/\\\/finance.sina.com.cn\\\/tech\\\/it\\\/2026-06-26\\\/doc-inietwvm7214086.shtml\",\"https:\\\/\\\/tech.sina.com.cn\\\/it\\\/2026-06-26\\\/doc-inietwvm7214086.shtml\"]","templateid":"0","lids":"24,37,1144,1153,1548,1716,2114,2128,2431,2509,2515,2600,2603,2605,3318","productid":"0","wapurls":"[\"https:\\\/\\\/finance.sina.cn\\\/tech\\\/2026-06-26\\\/detail-inietwvm7214086.d.html\",\"http:\\\/\\\/finance.sina.cn\\\/tech\\\/2026-06-26\\\/detail-inietwvm7214086.d.html\",\"https:\\\/\\\/tech.sina.cn\\\/it\\\/2026-06-26\\\/detail-inietwvm7214086.d.html\",\"http:\\\/\\\/tech.sina.cn\\\/it\\\/2026-06-26\\\/detail-inietwvm7214086.d.html\"]","summary":"","url":"https:\/\/finance.sina.com.cn\/tech\/it\/2026-06-26\/doc-inietwvm7214086.shtml","authoruid":"0","wapsummary":"","level":"2"},{"icons":"","is_cre_manual":"0","hqChart":"{\"stockCharts\":\"no\",\"stockCode\":\"\",\"stockMarket\":\"\",\"mulStockChart\":\"\",\"isStaticStock\":\"\"}","intime":"1782474025","channelid":"31","ctime":"1782473655","mtime":"1782474013","authoruid":"0","level":"2","vid":"0","ipad_vid":"0","video_time_length":"0","categoryid":"1","mediaid":"0","templateid":"0","productid":"0","ext_0":"0","ext_1":"0","ext_2":"0","ext_3":"0","ext_4":"0","docid":"comos:nietwvm7218226","url":"https:\/\/finance.sina.com.cn\/stock\/s\/2026-06-26\/doc-inietwvm7218226.shtml","urls":"[\"https:\\\/\\\/finance.sina.com.cn\\\/stock\\\/s\\\/2026-06-26\\\/doc-inietwvm7218226.shtml\"]","wapurl":"https:\/\/finance.sina.cn\/stock\/ssgs\/2026-06-26\/detail-inietwvm7218226.d.html","wapurls":"[\"https:\\\/\\\/finance.sina.cn\\\/stock\\\/ssgs\\\/2026-06-26\\\/detail-inietwvm7218226.d.html\",\"http:\\\/\\\/finance.sina.cn\\\/stock\\\/ssgs\\\/2026-06-26\\\/detail-inietwvm7218226.d.html\"]","wapsummary":"","title":"\u6700\u9ad8\u6da8\u8d85650%\uff01001399\u4e0a\u5e02\u9996\u65e5\uff0c\u4e24\u5ea6\u4e34\u505c","stitle":"","summary":"","intro":" 6\u670826\u65e5\uff0c\u60e0\u79d1\u80a1\u4efd\u6b63\u5f0f\u767b\u9646\u6df1\u4ea4\u6240\u4e3b\u677f\u3002\u4e0a\u5e02\u9996\u65e5\u516c\u53f8\u4ea4\u6295\u6d3b\u8dc3\uff0c\u80a1\u4ef7\u5927\u5e45\u4e0a\u6da8\u5e76\u4e24\u5ea6\u89e6\u53d1\u4e34\u65f6\u505c\u724c\u3002\u622a\u81f3\u6536\u76d8\uff0c\u516c\u53f8\u80a1\u4ef7\u62a542\u5143\/\u80a1\uff0c\u8f83\u53d1\u884c\u4ef7\u4e0a\u6da8315.02%\uff0c\u603b\u5e02\u503c3065\u4ebf\u5143\u3002","author":"","commentid":"cj:comos-nietwvm7218226:0","video_id":"","keywords":"","media_name":"\u4e0a\u6d77\u8bc1\u5238\u62a5","columnid":"1850,1884","subjectid":"","img":[],"images":[{"u":"http:\/\/n.sinaimg.cn\/blog\/crawl\/88\/w550h338\/20260626\/5816-518054263b9131624c88b22066cac9be.jpg","w":"550","h":"338","t":""},{"u":"http:\/\/n.sinaimg.cn\/blog\/crawl\/463\/w550h713\/20260626\/f221-371299381b1eab0bac9f811c4817f538.jpg","w":"550","h":"713","t":""},{"u":"http:\/\/n.sinaimg.cn\/blog\/crawl\/745\/w550h195\/20260626\/dc1c-ca1b5581c7fb0d82a6b6b9a9e0690626.jpg","w":"550","h":"195","t":""}],"lids":"295,751,2509,2516,2517,2519,2544,2671,3318","oid":"868298935"},{"icons":"","is_cre_manual":"0","hqChart":"{\"stockCharts\":\"no\",\"stockCode\":\"\",\"stockMarket\":\"\",\"mulStockChart\":\"\",\"isStaticStock\":\"\"}","intime":"1782473918","channelid":"31","ctime":"1782473655","mtime":"1782473914","authoruid":"0","level":"2","vid":"0","ipad_vid":"0","video_time_length":"0","categoryid":"1","mediaid":"0","templateid":"0","productid":"0","ext_0":"0","ext_1":"0","ext_2":"0","ext_3":"0","ext_4":"0","docid":"comos:nietwvm7217023","url":"https:\/\/finance.sina.com.cn\/stock\/s\/2026-06-26\/doc-inietwvm7217023.shtml","urls":"[\"https:\\\/\\\/finance.sina.com.cn\\\/stock\\\/s\\\/2026-06-26\\\/doc-inietwvm7217023.shtml\"]","wapurl":"https:\/\/finance.sina.cn\/stock\/ssgs\/2026-06-26\/detail-inietwvm7217023.d.html","wapurls":"[\"https:\\\/\\\/finance.sina.cn\\\/stock\\\/ssgs\\\/2026-06-26\\\/detail-inietwvm7217023.d.html\",\"http:\\\/\\\/finance.sina.cn\\\/stock\\\/ssgs\\\/2026-06-26\\\/detail-inietwvm7217023.d.html\"]","wapsummary":"","title":"\u96ea\u677e\u53d1\u5c55\u5b9e\u63a7\u4eba\uff0c\u65e0\u671f\u5f92\u5211","stitle":"","summary":"","intro":"6\u670826\u65e5\u665a\u95f4\uff0cST\u96ea\u53d1\u53d1\u5e03\u5173\u4e8e\u5b9e\u9645\u63a7\u5236\u4eba\u6d89\u53ca\u6848\u4ef6\u60c5\u51b5\u7684\u8fdb\u5c55\u516c\u544a\u79f0\uff0c\u8fd1\u65e5\uff0c\u516c\u53f8\u83b7\u6089\uff0c\u5e7f\u4e1c\u7701\u9ad8\u7ea7\u4eba\u6c11\u6cd5\u9662\uff08\u4ee5\u4e0b\u7b80\u79f0\u201c\u5e7f\u4e1c\u9ad8\u9662\u201d\uff09\u5bf9\u516c\u53f8\u5b9e\u9645\u63a7\u5236\u4eba\u5f20\u52b2\u56e0\u96c6\u8d44\u8bc8\u9a97...","author":"","commentid":"cj:comos-nietwvm7217023:0","video_id":"","keywords":"","media_name":"\u4e0a\u6d77\u8bc1\u5238\u62a5","columnid":"1850,1884","subjectid":"","img":[],"images":[{"u":"http:\/\/n.sinaimg.cn\/blog\/crawl\/42\/w550h292\/20260626\/2650-04d561115f8aad48b85211752069c86b.png","w":"550","h":"292","t":""}],"lids":"295,751,2509,2516,2517,2519,2544,2671,3318","oid":"868298254"},{"hqChart":"{\"stockCharts\":\"no\",\"stockCode\":\"\",\"stockMarket\":\"\",\"mulStockChart\":\"\",\"isStaticStock\":\"\"}","categoryid":"1","intro":"\u5468\u4e94\uff086\u670826\u65e5\uff09\uff0c\u4e9a\u592a\u80a1\u5e02\u5168\u7ebf\u4e0b\u632b\uff0c\u97e9\u80a1\u76d8\u4e2d\u518d\u5ea6\u89e6\u53d1\u7194\u65ad\u3002A\u80a1\u5e02\u573a\u8d854600\u80a1\u4e0b\u8dcc\uff0c\u6caa\u6307\u6536\u8dcc2.26%\u9000\u5b884000\u70b9\uff0c\u521b\u6307\u91cd\u632b4.07%\u3002\u5e02\u573a\u4ea4\u6295\u6d3b\u8dc3\u5ea6\u4ecd\u9ad8\uff0c\u6210\u4ea4\u989d\u8d853.57\u4e07\u4ebf\u5143...","mediaid":"0","summary":"","wapurls":"[\"https:\\\/\\\/finance.sina.cn\\\/fund\\\/etf\\\/2026-06-26\\\/detail-inietwvq5123212.d.html\",\"http:\\\/\\\/finance.sina.cn\\\/fund\\\/etf\\\/2026-06-26\\\/detail-inietwvq5123212.d.html\"]","productid":"0","is_cre_manual":"0","ctime":"1782473611","url":"https:\/\/finance.sina.com.cn\/money\/fund\/etf\/2026-06-26\/doc-inietwvq5123212.shtml","stitle":"","authoruid":"0","wapsummary":"","level":"2","columnid":"1956","wapurl":"https:\/\/finance.sina.cn\/fund\/etf\/2026-06-26\/detail-inietwvq5123212.d.html","oid":"868298225","img":[],"subjectid":"","ipad_vid":"0","commentid":"cj:comos-nietwvq5123212:0","vid":"0","video_id":"","channelid":"31","intime":"1782473869","video_time_length":"0","author":"","images":[{"u":"http:\/\/n.sinaimg.cn\/blog\/transform\/745\/w550h195\/20260626\/a6cb-3aadb5c4947b7ce23263b63f7dcf775c.png","w":"550","h":"195","t":""},{"u":"http:\/\/n.sinaimg.cn\/blog\/transform\/18\/w550h268\/20260626\/96fa-46bcb0d915328b129c3da5f2d8aa1396.png","w":"550","h":"268","t":""},{"u":"http:\/\/n.sinaimg.cn\/blog\/transform\/110\/w550h360\/20260626\/ce63-3b219d73e39b53e3e66e7cfbfac64f41.png","w":"550","h":"360","t":""},{"u":"http:\/\/n.sinaimg.cn\/blog\/transform\/675\/w550h125\/20260626\/5ed7-eef32497dea8980b180dae71c5d66438.png","w":"550","h":"125","t":""},{"u":"http:\/\/n.sinaimg.cn\/blog\/transform\/101\/w550h351\/20260626\/ede1-ed23d99558c5b13ca835ae19ecced0ca.png","w":"550","h":"351","t":""},{"u":"http:\/\/n.sinaimg.cn\/blog\/transform\/121\/w550h371\/20260626\/40d7-fafd192a350988d1de002d6b7b3ac442.png","w":"550","h":"371","t":""},{"u":"http:\/\/n.sinaimg.cn\/blog\/transform\/773\/w550h223\/20260626\/b316-db72ec33d28b3679e119e0b1e90e04e4.png","w":"550","h":"223","t":""},{"u":"http:\/\/n.sinaimg.cn\/blog\/transform\/159\/w550h409\/20260626\/4c08-45e04a3c9476ca5d778813c8eb70b069.png","w":"550","h":"409","t":""},{"u":"http:\/\/n.sinaimg.cn\/blog\/transform\/783\/w550h233\/20260626\/93fb-021abf16e9d9d63137a08c5968f6675b.png","w":"550","h":"233","t":""}],"keywords":"","icons":"","mtime":"1782473863","media_name":"\u65b0\u6d6a\u57fa\u91d1","ext_0":"0","ext_1":"0","ext_2":"0","title":"\u9000\u5b884000\u70b9\uff01\u201cAI\u4ea4\u6613\u201d\u7a81\u53d8\uff0c\u521b\u4e1a\u677f\u4eba\u5de5\u667a\u80fdETF\u632b\u903e5%\uff0c159131\u83b7\u5de8\u989d\u7533\u8d2d\uff01\u4f4e\u4f30\u677f\u5757\u6297\u8dcc\uff0c\u519c\u7267\u6e14\u9006\u5e02\u6536\u7ea2","ext_3":"0","docid":"comos:nietwvq5123212","ext_4":"0","urls":"[\"https:\\\/\\\/finance.sina.com.cn\\\/money\\\/fund\\\/etf\\\/2026-06-26\\\/doc-inietwvq5123212.shtml\"]","templateid":"0","lids":"295,1057,2509,2519,2544,3318"},{"icons":"","is_cre_manual":"0","hqChart":"{\"stockCharts\":\"no\",\"stockCode\":\"\",\"stockMarket\":\"\",\"mulStockChart\":\"\",\"isStaticStock\":\"\"}","intime":"1782473528","channelid":"31","ctime":"1782473521","mtime":"1782473521","authoruid":"0","level":"2","vid":"0","ipad_vid":"0","video_time_length":"0","categoryid":"1","mediaid":"0","columnid":"1956","templateid":"0","productid":"0","ext_0":"0","ext_1":"0","ext_2":"0","ext_3":"0","ext_4":"0","docid":"comos:nietwvs1898278","url":"https:\/\/finance.sina.com.cn\/money\/fund\/etf\/2026-06-26\/doc-inietwvs1898278.shtml","urls":"[\"https:\\\/\\\/finance.sina.com.cn\\\/money\\\/fund\\\/etf\\\/2026-06-26\\\/doc-inietwvs1898278.shtml\"]","wapurl":"https:\/\/finance.sina.cn\/fund\/etf\/2026-06-26\/detail-inietwvs1898278.d.html","wapurls":"[\"https:\\\/\\\/finance.sina.cn\\\/fund\\\/etf\\\/2026-06-26\\\/detail-inietwvs1898278.d.html\",\"http:\\\/\\\/finance.sina.cn\\\/fund\\\/etf\\\/2026-06-26\\\/detail-inietwvs1898278.d.html\"]","wapsummary":"","title":"\u4e07\u4ebf\u5149\u6a21\u5757\u5de8\u5934\u91cd\u632b\uff0c\u9ad8\u201c\u5149\u201d\u521b\u4e1a\u677f\u4eba\u5de5\u667a\u80fdETF\uff08159363\uff09\u8dcc\u8d855%\uff0c\u8d44\u91d1\u9022\u8dcc\u626b\u8d27\uff01\u673a\u6784\uff1a\u4ecd\u770b\u597dAI\u4ea4\u6613","stitle":"","summary":"","intro":" \u5468\u4e94\uff086\u670826\u65e5\uff09\uff0cAI\u4ea4\u6613\u964d\u6e29\uff0c\u5149\u6a21\u5757CPO\u5168\u7ebf\u4e0b\u632b\uff0c\u65b0\u6613\u76db\u3001\u5929\u5b5a\u901a\u4fe1\u8dcc\u8d857%\uff0c\u4e07\u4ebf\u5de8\u5934\u4e2d\u9645\u65ed\u521b\u8dcc\u8d855%\uff0c\u592a\u8fb0\u5149\u3001\u5146\u9f99\u4e92\u8fde\u3001\u8054\u7279\u79d1\u6280\u3001\u5149\u5e93\u79d1\u6280\u7b49\u591a\u80a1\u8dcc\u8d858%\u3002","author":"","commentid":"cj:comos-nietwvs1898278:0","video_id":"","keywords":"","media_name":"\u65b0\u6d6a\u57fa\u91d1","subjectid":"","img":[],"images":[{"u":"http:\/\/n.sinaimg.cn\/blog\/transform\/121\/w550h371\/20260626\/ee61-c61deaf9b961d841e73591a6a6307ba2.png","w":"550","h":"371","t":""}],"lids":"295,1057,2509,2519,2544,3318","oid":"868296227"},{"icons":"","is_cre_manual":"0","hqChart":"{\"stockCharts\":\"no\",\"stockCode\":\"002912\",\"stockMarket\":\"sz\",\"mulStockChart\":\"\",\"isStaticStock\":\"\"}","intime":"1782474141","channelid":"31","ctime":"1782473501","mtime":"1782474136","authoruid":"0","level":"2","vid":"0","ipad_vid":"0","video_time_length":"0","categoryid":"1","mediaid":"0","columnid":"1850","templateid":"0","productid":"0","ext_0":"0","ext_1":"0","ext_2":"0","ext_3":"0","ext_4":"0","docid":"comos:nietwvq5125849","url":"https:\/\/finance.sina.com.cn\/stock\/relnews\/cn\/2026-06-26\/doc-inietwvq5125849.shtml","urls":"[\"https:\\\/\\\/finance.sina.com.cn\\\/stock\\\/relnews\\\/cn\\\/2026-06-26\\\/doc-inietwvq5125849.shtml\"]","wapurl":"https:\/\/finance.sina.cn\/2026-06-26\/detail-inietwvq5125849.d.html","wapurls":"[\"https:\\\/\\\/finance.sina.cn\\\/2026-06-26\\\/detail-inietwvq5125849.d.html\",\"http:\\\/\\\/finance.sina.cn\\\/2026-06-26\\\/detail-inietwvq5125849.d.html\"]","wapsummary":"","title":"\u4e2d\u65b0\u8d5b\u514b\uff1a\u516c\u53f8\u575a\u6301\u201cToG+ToB\u201d\u53cc\u8f6e\u9a71\u52a8","stitle":"","summary":"","intro":"\u8bc1\u5238\u65e5\u62a5\u7f516\u670826\u65e5\u8baf\uff0c\u4e2d\u65b0\u8d5b\u514b\u5728\u63a5\u53d7\u8c03\u7814\u8005\u63d0\u95ee\u65f6\u8868\u793a\uff0c\u516c\u53f8\u575a\u6301\u201cToG+ToB\u201d\u53cc\u8f6e\u9a71\u52a8\uff0c\u56fd\u5185\u56fd\u9645\u5747\u8861\u53d1\u5c55\u7684\u6574\u4f53\u6218\u7565\uff0c\u672c\u5e74\u5ea6\u7ee7\u7eed\u5c06\u6d77\u5916\u4e1a\u52a1\u4f5c\u4e3a\u91cd\u8981\u6295\u5165\u65b9\u5411\u4e4b\u4e00...","author":"","commentid":"cj:comos-nietwvq5125849:0","video_id":"","keywords":"","media_name":"\u8bc1\u5238\u65e5\u62a5\u7f51","subjectid":"","img":{"u":"http:\/\/n.sinaimg.cn\/finance\/c30320b4\/20210712\/wx_poster_finance1.png","w":100,"h":100,"t":""},"images":[],"lids":"295,2509,2517,2519,2544,2671,3318","oid":"868299574"},{"icons":"","is_cre_manual":"0","hqChart":"{\"stockCharts\":\"no\",\"stockCode\":\"\",\"stockMarket\":\"\",\"mulStockChart\":\"\",\"isStaticStock\":\"\"}","intime":"1782473336","channelid":"31","ctime":"1782473325","mtime":"1782473325","authoruid":"0","level":"2","vid":"0","ipad_vid":"0","video_time_length":"0","categoryid":"1","mediaid":"0","columnid":"1850","templateid":"0","productid":"0","ext_0":"0","ext_1":"0","ext_2":"0","ext_3":"0","ext_4":"0","docid":"comos:nietwvk0432181","url":"https:\/\/finance.sina.com.cn\/stock\/aigcy\/2026-06-26\/doc-inietwvk0432181.shtml","urls":"[\"https:\\\/\\\/finance.sina.com.cn\\\/stock\\\/aigcy\\\/2026-06-26\\\/doc-inietwvk0432181.shtml\"]","wapurl":"https:\/\/finance.sina.cn\/2026-06-26\/detail-inietwvk0432181.d.html","wapurls":"[\"https:\\\/\\\/finance.sina.cn\\\/2026-06-26\\\/detail-inietwvk0432181.d.html\",\"http:\\\/\\\/finance.sina.cn\\\/2026-06-26\\\/detail-inietwvk0432181.d.html\"]","wapsummary":"","title":"\u793c\u90a6\u533b\u836f\u6e2f\u80a1\u4e0a\u5e02\u5728\u5373\uff1a\u80be\u75c5\u8d5b\u9053\u7a00\u7f3a\u521b\u65b0\u5e73\u53f0\u8c6a\u534e\u57fa\u77f3\u6491\u573a\u677f\u5757\u8c03\u6574\u4e0b\u4f30\u503c\u4e0e\u5546\u4e1a\u5316\u8282\u594f\u6210\u6838\u5fc3\u770b\u70b9","stitle":"","summary":"","intro":"\u81ea2025\u5e749\u6708\u81f3\u4eca\uff0c\u6052\u751f\u751f\u7269\u79d1\u6280\u6307\u6570\u7d2f\u8ba1\u8dcc\u5e45\u8d8530%\uff0c\u6e2f\u80a118A\u672a\u76c8\u5229\u521b\u65b0\u836f\u4f01\u6574\u4f53\u4f30\u503c\u4e2d\u67a2\u6301\u7eed\u4e0b\u79fb\uff0c\u5e02\u573a\u6295\u8d44\u903b\u8f91\u9010\u6b65\u4ece\u8d5b\u9053\u70ed\u5ea6\u8f6c\u5411\u4e34\u5e8a\u5151\u73b0\u80fd\u529b...","author":"","commentid":"cj:comos-nietwvk0432181:0","video_id":"","keywords":"","media_name":"\u65b0\u6d6a\u8bc1\u5238","subjectid":"","img":{"u":"http:\/\/n.sinaimg.cn\/finance\/c30320b4\/20210712\/wx_poster_finance1.png","w":100,"h":100,"t":""},"images":[],"lids":"295,2509,2517,2519,2544,2671,3318","oid":"868295586"},{"icons":"","is_cre_manual":"0","hqChart":"{\"stockCharts\":\"no\",\"stockCode\":\"\",\"stockMarket\":\"\",\"mulStockChart\":\"\",\"isStaticStock\":\"\"}","intime":"1782474151","channelid":"31","ctime":"1782473279","mtime":"1782474145","authoruid":"0","level":"2","vid":"0","ipad_vid":"0","video_time_length":"0","categoryid":"1","mediaid":"0","columnid":"1850","templateid":"0","productid":"0","ext_0":"0","ext_1":"0","ext_2":"0","ext_3":"0","ext_4":"0","docid":"comos:nietwvm7210206","url":"https:\/\/finance.sina.com.cn\/stock\/relnews\/cn\/2026-06-26\/doc-inietwvm7210206.shtml","urls":"[\"https:\\\/\\\/finance.sina.com.cn\\\/stock\\\/relnews\\\/cn\\\/2026-06-26\\\/doc-inietwvm7210206.shtml\"]","wapurl":"https:\/\/finance.sina.cn\/2026-06-26\/detail-inietwvm7210206.d.html","wapurls":"[\"https:\\\/\\\/finance.sina.cn\\\/2026-06-26\\\/detail-inietwvm7210206.d.html\",\"http:\\\/\\\/finance.sina.cn\\\/2026-06-26\\\/detail-inietwvm7210206.d.html\"]","wapsummary":"","title":"\u9ea6\u683c\u7c73\u7279\u5411\u6e2f\u4ea4\u6240\u63d0\u4ea4\u4e0a\u5e02\u7533\u8bf7","stitle":"","summary":"","intro":"\u636e\u6e2f\u4ea4\u6240\u6587\u4ef6\uff0c6\u670826\u65e5\uff0c\u6df1\u5733\u9ea6\u683c\u7c73\u7279\u7535\u6c14\u80a1\u4efd\u6709\u9650\u516c\u53f8\u5411\u6e2f\u4ea4\u6240\u63d0\u4ea4\u4e0a\u5e02\u7533\u8bf7\u4e66\uff0c\u8054\u5e2d\u4fdd\u8350\u4eba\u4e3a\u534e\u6cf0\u56fd\u9645\u3001\u82b1\u65d7\u3002","author":"","commentid":"cj:comos-nietwvm7210206:0","video_id":"","keywords":"","media_name":"\u754c\u9762","subjectid":"","img":{"u":"http:\/\/n.sinaimg.cn\/finance\/c30320b4\/20210712\/wx_poster_finance1.png","w":100,"h":100,"t":""},"images":[],"lids":"295,2509,2517,2519,2544,2671,3318","oid":"868299581"},{"icons":"","is_cre_manual":"0","hqChart":"{\"stockCharts\":\"no\",\"stockCode\":\"\",\"stockMarket\":\"\",\"mulStockChart\":\"\",\"isStaticStock\":\"\"}","intime":"1782474162","channelid":"31","ctime":"1782473118","mtime":"1782474158","authoruid":"0","level":"2","vid":"0","ipad_vid":"0","video_time_length":"0","categoryid":"1","mediaid":"0","columnid":"1850","templateid":"0","productid":"0","ext_0":"0","ext_1":"0","ext_2":"0","ext_3":"0","ext_4":"0","docid":"comos:nietwvs1903004","url":"https:\/\/finance.sina.com.cn\/stock\/zqgd\/2026-06-26\/doc-inietwvs1903004.shtml","urls":"[\"https:\\\/\\\/finance.sina.com.cn\\\/stock\\\/zqgd\\\/2026-06-26\\\/doc-inietwvs1903004.shtml\"]","wapurl":"https:\/\/finance.sina.cn\/2026-06-26\/detail-inietwvs1903004.d.html","wapurls":"[\"https:\\\/\\\/finance.sina.cn\\\/2026-06-26\\\/detail-inietwvs1903004.d.html\",\"http:\\\/\\\/finance.sina.cn\\\/2026-06-26\\\/detail-inietwvs1903004.d.html\"]","wapsummary":"","title":"\u79d1\u91d1\u660eIPO\u72b6\u6001\u53d8\u66f4\u4e3a\u901a\u8fc7","stitle":"","summary":"","intro":"\u6839\u636e\u5317\u4ea4\u6240\u6700\u65b0\u62ab\u9732\u7684\u4fe1\u606f\uff0c2026\u5e746\u670826\u65e5\uff0c\u6df1\u5733\u5e02\u79d1\u91d1\u660e\u7535\u5b50\u80a1\u4efd\u6709\u9650\u516c\u53f8IPO\u7684\u72b6\u6001\u4ece\u5df2\u95ee\u8be2\u53d8\u66f4\u4e3a\u901a\u8fc7\u3002","author":"","commentid":"cj:comos-nietwvs1903004:0","video_id":"","keywords":"","media_name":"","subjectid":"","img":{"u":"http:\/\/n.sinaimg.cn\/finance\/c30320b4\/20210712\/wx_poster_finance1.png","w":100,"h":100,"t":""},"images":[],"lids":"295,2509,2517,2519,2544,2671,3318","oid":"868299600"}]}}